Workbook

Sheet Open Pipeline
A1: Open pipeline - FocusNet snapshot Tuesday 6 October 2026
A2: Weighted value = TCV x probability. Stalled = no logged activity for more than 45 days.
A3: Classification: Internal
A5: Opp ID | B5: Account ID | C5: Account | D5: Industry | E5: Opportunity | F5: Service line | G5: Offering | H5: Stage | I5: TCV (USD) | J5: Probability | K5: Weighted (USD) | L5: Close date | M5: Owner | N5: Partner | O5: Source | P5: Created | Q5: Last activity | R5: Days since activity | S5: Stalled flag | T5: Competitors | U5: Notes
A6: OPP-24240 | B6: ACC-1015 | C6: Halcyon Health | D6: Healthcare | E6: Claims Data Mart Fabric Migration (CR-0219) | F6: Data & AI | G6: Microsoft Fabric Analytics | H6: 1 - Qualify | I6: 450000 | J6: 0.3 | K6: =I6*J6 -> 135000 | L6: 46367 | M6: Hannah Lee | N6: Microsoft | O6: Change request | P6: 46295 | Q6: 46297 | R6: =DATE(2026,10,6)-Q6 -> 4 | S6: =IF(R6>45,"STALLED","") | U6: Value range $380K-$520K pending scope
A7: OPP-24101 | B7: ACC-1001 | C7: Northwind Traders | D7: Retail | E7: FY27 Managed AMS Renewal | F7: Managed Services | G7: Application Managed Services (AMS) | H7: 2 - Discover | I7: 4200000 | J7: 0.45 | K7: =I7*J7 -> 1890000 | L7: 46402 | M7: Priya Raman | O7: Account expansion | P7: 46175 | Q7: 46296 | R7: =DATE(2026,10,6)-Q7 -> 5 | S7: =IF(R7>45,"STALLED","") | T7: Infosys | U7: Renewal date 1 Feb 2027. At risk: Atlas red, CSAT 6.1, sponsor Daniel Okafor exited 28 Sep
A8: OPP-24160 | B8: ACC-1007 | C8: Adventure Works Retail | D8: Retail | E8: Unified Commerce Replatform | F8: Digital Commerce | G8: Unified Commerce Replatform | H8: 2 - Discover | I8: 2600000 | J8: 0.2 | K8: =I8*J8 -> 520000 | L8: 46472 | M8: James Patel | O8: Campaign CMP-2602 (sourced) | P8: 46245 | Q8: 46300 | R8: =DATE(2026,10,6)-Q8 -> 1 | S8: =IF(R8>45,"STALLED","") | T8: EPAM; Publicis Sapient | U8: RFI BID-0619 due 16 Oct; RFP expected mid-Nov
A9: OPP-24121 | B9: ACC-1003 | C9: Woodgrove Bank | D9: BFSI | E9: Managed SOC (MXDR) | F9: Cybersecurity | G9: Managed SOC (MXDR) | H9: 2 - Discover | I9: 900000 | J9: 0.25 | K9: =I9*J9 -> 225000 | L9: 46477 | M9: Marcus Bell | N9: Microsoft | O9: Campaign CMP-2601 (influenced) | P9: 46260 | Q9: 46287 | R9: =DATE(2026,10,6)-Q9 -> 14 | S9: =IF(R9>45,"STALLED","") | T9: Optiv
A10: OPP-24260 | B10: ACC-1010 | C10: Lamna Healthcare | D10: Healthcare | E10: GenAI Member Service Copilot | F10: Data & AI | G10: GenAI Copilot Accelerator | H10: 2 - Discover | I10: 600000 | J10: 0.25 | K10: =I10*J10 -> 150000 | L10: 46430 | M10: Hannah Lee | N10: Microsoft | O10: Campaign CMP-2603 (sourced) | P10: 46203 | Q10: 46282 | R10: =DATE(2026,10,6)-Q10 -> 19 | S10: =IF(R10>45,"STALLED","")
A11: OPP-24103 | B11: ACC-1001 | C11: Northwind Traders | D11: Retail | E11: Atlas Wave 3 Rollout Change Request | F11: Application Modernization | G11: POS Modernisation | H11: 2 - Discover | I11: 380000 | J11: 0.25 | K11: =I11*J11 -> 95000 | L11: 46371 | M11: Kavya Iyer | O11: Change request | P11: 46254 | Q11: 46295 | R11: =DATE(2026,10,6)-Q11 -> 6 | S11: =IF(R11>45,"STALLED","") | U11: On hold until wave 2 stabilises
A12: OPP-24230 | B12: ACC-1014 | C12: Calder Insurance | D12: BFSI | E12: Claims Modernisation (Guidewire ClaimCenter) | F12: Application Modernization | G12: Guidewire Implementation | H12: 3 - Solution | I12: 5800000 | J12: 0.35 | K12: =I12*J12 -> 2030000 | L12: 46416 | M12: Marcus Bell | N12: Guidewire | O12: RFP | P12: 46300 | Q12: 46302 | R12: =DATE(2026,10,6)-Q12 -> -1 | S12: =IF(R12>45,"STALLED","") | T12: Accenture; Cognizant; EY | U12: RFP BID-0618 received 5 Oct; submission due 20 Oct; AWS migration incentive up to $120K
A13: OPP-24210 | B13: ACC-1012 | C13: Trey Research | D13: Life Sciences | E13: GxP Data Lake on AWS | F13: Data & AI | G13: Snowflake Data Cloud | H13: 3 - Solution | I13: 1400000 | J13: 0.4 | K13: =I13*J13 -> 560000 | L13: 46444 | M13: Hannah Lee | N13: AWS | O13: Partner referral (AWS) | P13: 46219 | Q13: 46293 | R13: =DATE(2026,10,6)-Q13 -> 8 | S13: =IF(R13>45,"STALLED","") | T13: Slalom | U13: MAP mobilize funding applied
A14: OPP-24110 | B14: ACC-1002 | C14: Fabrikam Health | D14: Healthcare | E14: Patient Data Platform Phase 2 - Population Health | F14: Data & AI | G14: Microsoft Fabric Analytics | H14: 3 - Solution | I14: 1250000 | J14: 0.5 | K14: =I14*J14 -> 625000 | L14: 46416 | M14: Priya Raman | N14: Microsoft | O14: Campaign CMP-2603 (influenced) | P14: 46197 | Q14: 46295 | R14: =DATE(2026,10,6)-Q14 -> 6 | S14: =IF(R14>45,"STALLED","") | T14: Deloitte | U14: Depends on phase 1 Epic Clarity feed stabilising
A15: OPP-24171 | B15: ACC-1008 | C15: Wingtip Logistics | D15: Logistics | E15: Fleet Analytics Expansion - EU Depots | F15: Data & AI | G15: Cloud Data Platform (Azure Databricks) | H15: 3 - Solution | I15: 1200000 | J15: 0.6 | K15: =I15*J15 -> 720000 | L15: 46409 | M15: Sophie Turner | N15: Databricks | O15: Account expansion | P15: 46265 | Q15: 46301 | R15: =DATE(2026,10,6)-Q15 -> 0 | S15: =IF(R15>45,"STALLED","") | U15: Rotterdam and Hamburg depots open Q1 2027
A16: OPP-24150 | B16: ACC-1005 | C16: Litware Insurance | D16: BFSI | E16: Intelligent Underwriting Intake | F16: Intelligent Automation | G16: Intelligent Document Processing | H16: 3 - Solution | I16: 780000 | J16: 0.45 | K16: =I16*J16 -> 351000 | L16: 46374 | M16: Marcus Bell | N16: Microsoft | O16: Campaign CMP-2605 (sourced) | P16: 46233 | Q16: 46297 | R16: =DATE(2026,10,6)-Q16 -> 4 | S16: =IF(R16>45,"STALLED","") | T16: Genpact | U16: Lead LD-30418 (Samuel Price) converted by Aisha Khan
A17: OPP-24141 | B17: ACC-1006 | C17: Contoso Manufacturing | D17: Manufacturing | E17: SAP S/4HANA Data Migration Support | F17: Application Modernization | G17: SAP Data Migration | H17: 3 - Solution | I17: 650000 | J17: 0.4 | K17: =I17*J17 -> 260000 | L17: 46374 | M17: Sophie Turner | O17: Account expansion | P17: 46262 | Q17: 46294 | R17: =DATE(2026,10,6)-Q17 -> 7 | S17: =IF(R17>45,"STALLED","") | T17: Capgemini
A18: OPP-24102 | B18: ACC-1001 | C18: Northwind Traders | D18: Retail | E18: Loyalty Analytics Platform | F18: Data & AI | G18: Microsoft Fabric Analytics | H18: 3 - Solution | I18: 640000 | J18: 0.3 | K18: =I18*J18 -> 192000 | L18: 46356 | M18: Priya Raman | N18: Microsoft | O18: Account expansion | P18: 46126 | Q18: 46246 | R18: =DATE(2026,10,6)-Q18 -> 55 | S18: =IF(R18>45,"STALLED","") -> STALLED | U18: Stalled: no activity since 12 Aug; client focus shifted to Atlas recovery
A19: OPP-24120 | B19: ACC-1003 | C19: Woodgrove Bank | D19: BFSI | E19: Enterprise Data Platform Modernisation | F19: Data & AI | G19: Cloud Data Platform (Azure Databricks) | H19: 4 - Proposal | I19: 3100000 | J19: 0.55 | K19: =I19*J19 -> 1705000 | L19: 46346 | M19: Marcus Bell | N19: Microsoft | O19: Partner co-sell (Microsoft) | P19: 46161 | Q19: 46301 | R19: =DATE(2026,10,6)-Q19 -> 0 | S19: =IF(R19>45,"STALLED","") | T19: Accenture; Infosys | U19: RFP BID-0612 submitted 25 Sep; BAFO requested by 14 Oct; POC PRG-2004 running
A20: OPP-24220 | B20: ACC-1013 | C20: Meridian Bank | D20: BFSI | E20: Cloud Data Platform | F20: Data & AI | G20: Cloud Data Platform (Azure Databricks) | H20: 4 - Proposal | I20: 2400000 | J20: 0.58 | K20: =I20*J20 -> 1392000 | L20: 46374 | M20: Marcus Bell | N20: Microsoft | O20: Campaign CMP-2601 (sourced) | P20: 46239 | Q20: 46301 | R20: =DATE(2026,10,6)-Q20 -> 0 | S20: =IF(R20>45,"STALLED","") | T20: Accenture; Cognizant (incumbent DW) | U20: Win odds 58% (+11 pts in 3 weeks). CFO Grace Liu not met. Azure Innovate funding up to $150K applied
A21: OPP-24130 | B21: ACC-1004 | C21: Tailspin Airlines | D21: Travel & Transport | E21: Crew Operations Platform Modernisation | F21: Application Modernization | G21: Legacy to Cloud-Native | H21: 4 - Proposal | I21: 2200000 | J21: 0.5 | K21: =I21*J21 -> 1100000 | L21: 46318 | M21: Sophie Turner | N21: AWS | O21: RFP | P21: 46209 | Q21: 46295 | R21: =DATE(2026,10,6)-Q21 -> 6 | S21: =IF(R21>45,"STALLED","") | T21: TCS; Cognizant | U21: Orals held 30 Sep; decision expected 23 Oct
A22: OPP-24111 | B22: ACC-1002 | C22: Fabrikam Health | D22: Healthcare | E22: AMS Renewal FY27 | F22: Managed Services | G22: Application Managed Services (AMS) | H22: 4 - Proposal | I22: 1800000 | J22: 0.75 | K22: =I22*J22 -> 1350000 | L22: 46371 | M22: Priya Raman | O22: Account expansion | P22: 46211 | Q22: 46300 | R22: =DATE(2026,10,6)-Q22 -> 1 | S22: =IF(R22>45,"STALLED","")
A23: OPP-24190 | B23: ACC-1010 | C23: Lamna Healthcare | D23: Healthcare | E23: Claims Platform Azure Migration | F23: Cloud & Infrastructure | G23: Azure Landing Zone | H23: 4 - Proposal | I23: 1500000 | J23: 0.5 | K23: =I23*J23 -> 750000 | L23: 46356 | M23: Hannah Lee | N23: Microsoft | O23: Campaign CMP-2604 (sourced) | P23: 46169 | Q23: 46297 | R23: =DATE(2026,10,6)-Q23 -> 4 | S23: =IF(R23>45,"STALLED","") | T23: Kyndryl; NTT DATA | U23: RFP BID-0615 submitted 2 Oct after extension; AMM funding approved
A24: OPP-24200 | B24: ACC-1011 | C24: Wide World Importers | D24: Retail | E24: WMS Support Renewal FY27 | F24: Managed Services | G24: Application Managed Services (AMS) | H24: 4 - Proposal | I24: 1100000 | J24: 0.4 | K24: =I24*J24 -> 440000 | L24: 46325 | M24: James Patel | O24: Renewal | P24: 46204 | Q24: 46289 | R24: =DATE(2026,10,6)-Q24 -> 12 | S24: =IF(R24>45,"STALLED","") | T24: Wipro | U24: At risk: Wipro bid ~18% lower; CFO cost programme
A25: OPP-24180 | B25: ACC-1009 | C25: Relecloud | D25: Telecom | E25: AIOps Managed Services Renewal | F25: Managed Services | G25: AIOps Managed Services | H25: 5 - Negotiate | I25: 2400000 | J25: 0.85 | K25: =I25*J25 -> 2040000 | L25: 46339 | M25: James Patel | O25: Renewal | P25: 46188 | Q25: 46302 | R25: =DATE(2026,10,6)-Q25 -> -1 | S25: =IF(R25>45,"STALLED","") | U25: Contract end 30 Nov 2026
H27: Total | I27: =SUBTOTAL(9,I6:I25) -> 35350000 | K27: =SUBTOTAL(9,K6:K25) -> 16530000

Sheet By Stage
A1: Pipeline by stage
A2: SUMIFS over Open Pipeline
A3: Classification: Internal
A5: Stage | B5: Opportunities | C5: TCV (USD) | D5: Weighted (USD) | E5: Avg probability
A6: 1 - Qualify | B6: =COUNTIFS('Open Pipeline'!$H$6:$H$25,A6) -> 1 | C6: =SUMIFS('Open Pipeline'!$I$6:$I$25,'Open Pipeline'!$H$6:$H$25,A6) -> 450000 | D6: =SUMIFS('Open Pipeline'!$K$6:$K$25,'Open Pipeline'!$H$6:$H$25,A6) -> 135000 | E6: =IF(C6=0,"",D6/C6) -> 0.3
A7: 2 - Discover | B7: =COUNTIFS('Open Pipeline'!$H$6:$H$25,A7) -> 5 | C7: =SUMIFS('Open Pipeline'!$I$6:$I$25,'Open Pipeline'!$H$6:$H$25,A7) -> 8680000 | D7: =SUMIFS('Open Pipeline'!$K$6:$K$25,'Open Pipeline'!$H$6:$H$25,A7) -> 2880000 | E7: =IF(C7=0,"",D7/C7) -> 0.33179724
A8: 3 - Solution | B8: =COUNTIFS('Open Pipeline'!$H$6:$H$25,A8) -> 7 | C8: =SUMIFS('Open Pipeline'!$I$6:$I$25,'Open Pipeline'!$H$6:$H$25,A8) -> 11720000 | D8: =SUMIFS('Open Pipeline'!$K$6:$K$25,'Open Pipeline'!$H$6:$H$25,A8) -> 4738000 | E8: =IF(C8=0,"",D8/C8) -> 0.40426621
A9: 4 - Proposal | B9: =COUNTIFS('Open Pipeline'!$H$6:$H$25,A9) -> 6 | C9: =SUMIFS('Open Pipeline'!$I$6:$I$25,'Open Pipeline'!$H$6:$H$25,A9) -> 12100000 | D9: =SUMIFS('Open Pipeline'!$K$6:$K$25,'Open Pipeline'!$H$6:$H$25,A9) -> 6737000 | E9: =IF(C9=0,"",D9/C9) -> 0.55677686
A10: 5 - Negotiate | B10: =COUNTIFS('Open Pipeline'!$H$6:$H$25,A10) -> 1 | C10: =SUMIFS('Open Pipeline'!$I$6:$I$25,'Open Pipeline'!$H$6:$H$25,A10) -> 2400000 | D10: =SUMIFS('Open Pipeline'!$K$6:$K$25,'Open Pipeline'!$H$6:$H$25,A10) -> 2040000 | E10: =IF(C10=0,"",D10/C10) -> 0.85
A11: Total | B11: =SUM(B6:B10) -> 20 | C11: =SUM(C6:C10) -> 35350000 | D11: =SUM(D6:D10) -> 16530000
A14: By service line
A15: Service line | B15: Opportunities | C15: TCV (USD) | D15: Weighted (USD)
A16: Cloud & Infrastructure | B16: =COUNTIFS('Open Pipeline'!$F$6:$F$25,A16) -> 1 | C16: =SUMIFS('Open Pipeline'!$I$6:$I$25,'Open Pipeline'!$F$6:$F$25,A16) -> 1500000 | D16: =SUMIFS('Open Pipeline'!$K$6:$K$25,'Open Pipeline'!$F$6:$F$25,A16) -> 750000
A17: Data & AI | B17: =COUNTIFS('Open Pipeline'!$F$6:$F$25,A17) -> 8 | C17: =SUMIFS('Open Pipeline'!$I$6:$I$25,'Open Pipeline'!$F$6:$F$25,A17) -> 11040000 | D17: =SUMIFS('Open Pipeline'!$K$6:$K$25,'Open Pipeline'!$F$6:$F$25,A17) -> 5479000
A18: Application Modernization | B18: =COUNTIFS('Open Pipeline'!$F$6:$F$25,A18) -> 4 | C18: =SUMIFS('Open Pipeline'!$I$6:$I$25,'Open Pipeline'!$F$6:$F$25,A18) -> 9030000 | D18: =SUMIFS('Open Pipeline'!$K$6:$K$25,'Open Pipeline'!$F$6:$F$25,A18) -> 3485000
A19: Digital Commerce | B19: =COUNTIFS('Open Pipeline'!$F$6:$F$25,A19) -> 1 | C19: =SUMIFS('Open Pipeline'!$I$6:$I$25,'Open Pipeline'!$F$6:$F$25,A19) -> 2600000 | D19: =SUMIFS('Open Pipeline'!$K$6:$K$25,'Open Pipeline'!$F$6:$F$25,A19) -> 520000
A20: Managed Services | B20: =COUNTIFS('Open Pipeline'!$F$6:$F$25,A20) -> 4 | C20: =SUMIFS('Open Pipeline'!$I$6:$I$25,'Open Pipeline'!$F$6:$F$25,A20) -> 9500000 | D20: =SUMIFS('Open Pipeline'!$K$6:$K$25,'Open Pipeline'!$F$6:$F$25,A20) -> 5720000
A21: Cybersecurity | B21: =COUNTIFS('Open Pipeline'!$F$6:$F$25,A21) -> 1 | C21: =SUMIFS('Open Pipeline'!$I$6:$I$25,'Open Pipeline'!$F$6:$F$25,A21) -> 900000 | D21: =SUMIFS('Open Pipeline'!$K$6:$K$25,'Open Pipeline'!$F$6:$F$25,A21) -> 225000
A22: Intelligent Automation | B22: =COUNTIFS('Open Pipeline'!$F$6:$F$25,A22) -> 1 | C22: =SUMIFS('Open Pipeline'!$I$6:$I$25,'Open Pipeline'!$F$6:$F$25,A22) -> 780000 | D22: =SUMIFS('Open Pipeline'!$K$6:$K$25,'Open Pipeline'!$F$6:$F$25,A22) -> 351000

Sheet Movement W40-W41
A1: Pipeline movement: 29 Sep (W40) to 6 Oct (W41)
A2: Changes in stage, value, probability and close date
A3: Classification: Internal
A5: Opp ID | B5: Account | C5: Opportunity | D5: Change type | E5: Stage W40 | F5: Stage W41 | G5: TCV W40 | H5: TCV W41 | I5: Close W40 | J5: Close W41 | K5: Prob W40 | L5: Prob W41 | M5: Comment
A6: OPP-24101 | B6: Northwind Traders | C6: FY27 Managed AMS Renewal | D6: Probability down | E6: 2 - Discover | F6: 2 - Discover | G6: 4200000 | H6: 4200000 | I6: 46402 | J6: 46402 | K6: 0.6 | L6: 0.45 | M6: Risk raised after Atlas escalation and Infosys approach (Sofia Lindqvist, 1 Oct)
A7: OPP-24102 | B7: Northwind Traders | C7: Loyalty Analytics Platform | D7: Close date slipped; Probability down | E7: 3 - Solution | F7: 3 - Solution | G7: 640000 | H7: 640000 | I7: 46325 | J7: 46356 | K7: 0.35 | L7: 0.3 | M7: Stalled; close moved to 30 Nov at best
A8: OPP-24120 | B8: Woodgrove Bank | C8: Enterprise Data Platform Modernisation | E8: 4 - Proposal | F8: 4 - Proposal | G8: 3100000 | H8: 3100000 | I8: 46346 | J8: 46346 | K8: 0.55 | L8: 0.55
A9: OPP-24130 | B9: Tailspin Airlines | C9: Crew Operations Platform Modernisation | D9: Close date slipped | E9: 4 - Proposal | F9: 4 - Proposal | G9: 2200000 | H9: 2200000 | I9: 46311 | J9: 46318 | K9: 0.5 | L9: 0.5 | M9: Decision moved to 23 Oct after orals
A10: OPP-24141 | B10: Contoso Manufacturing | C10: SAP S/4HANA Data Migration Support | D10: Close date slipped | E10: 3 - Solution | F10: 3 - Solution | G10: 650000 | H10: 650000 | I10: 46353 | J10: 46374 | K10: 0.4 | L10: 0.4 | M10: Client RFP pushed to Dec
A11: OPP-24171 | B11: Wingtip Logistics | C11: Fleet Analytics Expansion - EU Depots | D11: Stage advanced; Value changed; Probability up | E11: 2 - Discover | F11: 3 - Solution | G11: 1150000 | H11: 1200000 | I11: 46409 | J11: 46409 | K11: 0.5 | L11: 0.6 | M11: Scope added Hamburg depot
A12: OPP-24190 | B12: Lamna Healthcare | C12: Claims Platform Azure Migration | D12: Stage advanced; Probability up | E12: 3 - Solution | F12: 4 - Proposal | G12: 1500000 | H12: 1500000 | I12: 46356 | J12: 46356 | K12: 0.45 | L12: 0.5 | M12: RFP submitted 2 Oct
A13: OPP-24200 | B13: Wide World Importers | C13: WMS Support Renewal FY27 | D13: Probability down | E13: 4 - Proposal | F13: 4 - Proposal | G13: 1100000 | H13: 1100000 | I13: 46325 | J13: 46325 | K13: 0.55 | L13: 0.4 | M13: Wipro undercut ~18%
A14: OPP-24220 | B14: Meridian Bank | C14: Cloud Data Platform | D14: Probability up | E14: 4 - Proposal | F14: 4 - Proposal | G14: 2400000 | H14: 2400000 | I14: 46374 | J14: 46374 | K14: 0.47 | L14: 0.58 | M14: Shortlisted; strong orals prep; win odds 58%
A15: OPP-24230 | B15: Calder Insurance | C15: Claims Modernisation (Guidewire ClaimCenter) | D15: New | F15: 3 - Solution | G15: 0 | H15: 5800000 | J15: 46416 | L15: 0.35 | M15: Created this week
A16: OPP-24240 | B16: Halcyon Health | C16: Claims Data Mart Fabric Migration (CR-0219) | D16: New | F16: 1 - Qualify | G16: 0 | H16: 450000 | J16: 46367 | L16: 0.3 | M16: Created this week

Sheet Stalled Deals
A1: Stalled deals (no activity > 45 days) and ageing in stage
A2: Review in Monday pipeline call
A3: Classification: Internal
A5: Opp ID | B5: Account | C5: Opportunity | D5: Stage | E5: TCV (USD) | F5: Last activity | G5: Days idle | H5: Owner | I5: Reason | J5: Next step
A6: OPP-24102 | B6: Northwind Traders | C6: Loyalty Analytics Platform | D6: 3 - Solution | E6: 640000 | F6: 46246 | G6: 55 | H6: Priya Raman | I6: Client focus on Atlas recovery | J6: Restart after Atlas green; position with Sofia Lindqvist in Q1
A7: OPP-24101 | B7: Northwind Traders | C7: FY27 Managed AMS Renewal | D7: 2 - Discover | E7: 4200000 | F7: 46296 | G7: 5 | H7: Priya Raman | I7: No response from sponsor | J7: Owner to re-engage

Sheet Closed FY2026
A1: Closed opportunities in 2026
A2: Won and lost, by close date
A3: Classification: Internal
A5: Opp ID | B5: Account | C5: Opportunity | D5: Service line | E5: Result | F5: TCV (USD) | G5: Close date | H5: Owner | I5: Notes
A6: OPP-24320 | B6: Contoso Manufacturing | C6: MES Support Renewal | D6: Managed Services | E6: Closed Won | F6: 980000 | G6: 46052 | H6: Sophie Turner
A7: OPP-24310 | B7: Woodgrove Bank | C7: Service Desk Extension | D7: Managed Services | E7: Closed Won | F7: 560000 | G7: 46080 | H7: Marcus Bell
A8: OPP-24340 | B8: Trey Research | C8: Lab Data Integration Pilot | D8: Data & AI | E8: Closed Won | F8: 260000 | G8: 46094 | H8: Hannah Lee
A9: OPP-24300 | B9: Fabrikam Health | C9: AMS Scope Extension - Revenue Cycle Apps | D9: Managed Services | E9: Closed Won | F9: 420000 | G9: 46101 | H9: Priya Raman
A10: OPP-24270 | B10: Alpine Ski House | C10: Resort Systems Cloud Migration | D10: Cloud & Infrastructure | E10: Closed Won | F10: 320000 | G10: 46129 | H10: James Patel | I10: New logo
A11: OPP-24250 | B11: Relecloud | C11: Zero Trust Assessment | D11: Cybersecurity | E11: Closed Won | F11: 180000 | G11: 46147 | H11: James Patel
A12: OPP-24330 | B12: Adventure Works Retail | C12: Store Ops Analytics | D12: Data & AI | E12: Closed Lost | F12: 450000 | G12: 46171 | H12: James Patel | I12: Lost on timeline; incumbent extended
A13: OPP-24131 | B13: Tailspin Airlines | C13: AWS Migration Factory Wave 2 | D13: Cloud & Infrastructure | E13: Closed Won | F13: 1100000 | G13: 46185 | H13: Sophie Turner | I13: MAP credits applied
A14: OPP-24280 | B14: Fourth Coffee | C14: Mobile Order & Pay Commerce Build | D14: Digital Commerce | E14: Closed Won | F14: 410000 | G14: 46199 | H14: James Patel | I14: New logo
A15: OPP-24170 | B15: Wingtip Logistics | C15: Predictive Maintenance Phase 2 | D15: Data & AI | E15: Closed Won | F15: 850000 | G15: 46223 | H15: Sophie Turner
A16: OPP-24350 | B16: Relecloud | C16: OSS/BSS Modernisation Discovery | D16: Application Modernization | E16: Closed Lost | F16: 1600000 | G16: 46234 | H16: James Patel | I16: Lost: telecom OSS depth
A17: OPP-24140 | B17: Contoso Manufacturing | C17: Smart Factory IoT Data Platform | D17: Data & AI | E17: Closed Lost | F17: 1900000 | G17: 46248 | H17: Sophie Turner | I17: Lost to Capgemini on price (+14%) and OT/IoT references
A18: OPP-24290 | B18: Proseware Inc | C18: SaaS Platform Re-architecture | D18: Application Modernization | E18: Closed Won | F18: 280000 | G18: 46262 | H18: Hannah Lee | I18: New logo
