Workbook

Sheet Revenue Data
A1: SysHCM revenue actuals - January 2025 to September 2026 (USD)
A2: Recognised revenue by customer and service line. Margin % is restricted to Sales Ops / Finance.
A3: Classification: Confidential
A5: Period | B5: Month start | C5: Year | D5: Account ID | E5: Account | F5: Industry | G5: SL code | H5: Service line | I5: Revenue (USD) | J5: Delivery cost (USD) | K5: Gross margin %
A6: 2025-01 | B6: 45658 | C6: 2025 | D6: ACC-1001 | E6: Northwind Traders | F6: Retail | G6: CI | H6: Cloud & Infrastructure | I6: 43881.1 | J6: 33454.95 | K6: =IF(I6=0,0,(I6-J6)/I6) -> 0.2376
A7: 2025-01 | B7: 45658 | C7: 2025 | D7: ACC-1001 | E7: Northwind Traders | F7: Retail | G7: MS | H7: Managed Services | I7: 111267.8 | J7: 79489.72 | K7: =IF(I7=0,0,(I7-J7)/I7) -> 0.2856
A8: 2025-01 | B8: 45658 | C8: 2025 | D8: ACC-1002 | E8: Fabrikam Health | F8: Healthcare | G8: MS | H8: Managed Services | I8: 49181.04 | J8: 37628.41 | K8: =IF(I8=0,0,(I8-J8)/I8) -> 0.2349
A9: 2025-01 | B9: 45658 | C9: 2025 | D9: ACC-1003 | E9: Woodgrove Bank | F9: BFSI | G9: MS | H9: Managed Services | I9: 55582.38 | J9: 39235.6 | K9: =IF(I9=0,0,(I9-J9)/I9) -> 0.2941
A10: 2025-01 | B10: 45658 | C10: 2025 | D10: ACC-1003 | E10: Woodgrove Bank | F10: BFSI | G10: SEC | H10: Cybersecurity | I10: 19805.74 | J10: 13014.35 | K10: =IF(I10=0,0,(I10-J10)/I10) -> 0.3429
A11: 2025-01 | B11: 45658 | C11: 2025 | D11: ACC-1004 | E11: Tailspin Airlines | F11: Travel & Transport | G11: CI | H11: Cloud & Infrastructure | I11: 103161.29 | J11: 78650.17 | K11: =IF(I11=0,0,(I11-J11)/I11) -> 0.2376
A12: 2025-01 | B12: 45658 | C12: 2025 | D12: ACC-1004 | E12: Tailspin Airlines | F12: Travel & Transport | G12: MS | H12: Managed Services | I12: 31784.57 | J12: 21823.29 | K12: =IF(I12=0,0,(I12-J12)/I12) -> 0.3134
A13: 2025-01 | B13: 45658 | C13: 2025 | D13: ACC-1005 | E13: Litware Insurance | F13: BFSI | G13: IA | H13: Intelligent Automation | I13: 22547.56 | J13: 14825.02 | K13: =IF(I13=0,0,(I13-J13)/I13) -> 0.3425
A14: 2025-01 | B14: 45658 | C14: 2025 | D14: ACC-1006 | E14: Contoso Manufacturing | F14: Manufacturing | G14: AM | H14: Application Modernization | I14: 68946.27 | J14: 53950.46 | K14: =IF(I14=0,0,(I14-J14)/I14) -> 0.2175
A15: 2025-01 | B15: 45658 | C15: 2025 | D15: ACC-1006 | E15: Contoso Manufacturing | F15: Manufacturing | G15: MS | H15: Managed Services | I15: 37091.74 | J15: 26094.04 | K15: =IF(I15=0,0,(I15-J15)/I15) -> 0.2965
A16: 2025-01 | B16: 45658 | C16: 2025 | D16: ACC-1007 | E16: Adventure Works Retail | F16: Retail | G16: DC | H16: Digital Commerce | I16: 45089.13 | J16: 34511.22 | K16: =IF(I16=0,0,(I16-J16)/I16) -> 0.2346
A17: 2025-01 | B17: 45658 | C17: 2025 | D17: ACC-1008 | E17: Wingtip Logistics | F17: Logistics | G17: MS | H17: Managed Services | I17: 15049.28 | J17: 10590.18 | K17: =IF(I17=0,0,(I17-J17)/I17) -> 0.2963
... A445: 2026-09 | B445: 46266 | C445: 2026 | D445: ACC-1018 | E445: Proseware Inc | F445: Technology | G445: AM | H445: Application Modernization | I445: 49024.02 | J445: 38214.22 | K445: =IF(I445=0,0,(I445-J445)/I445) -> 0.2205

Sheet By Account (Monthly)
A1: Revenue by account by month (USD)
A2: SUMIFS over Revenue Data
A3: Classification: Confidential
A5: Account ID | B5: Account | C5: Jan-25 | D5: Feb-25 | E5: Mar-25 | F5: Apr-25 | G5: May-25 | H5: Jun-25 | I5: Jul-25 | J5: Aug-25 | K5: Sep-25 | L5: Oct-25 | M5: Nov-25 | N5: Dec-25 | O5: Jan-26 | P5: Feb-26 | Q5: Mar-26 | R5: Apr-26 | S5: May-26 | T5: Jun-26 | U5: Jul-26 | V5: Aug-26 | W5: Sep-26 | X5: FY2025 | Y5: 2026 YTD
A6: ACC-1001 | B6: Northwind Traders | C6: =SUMIFS('Revenue Data'!$I$6:$I$445,'Revenue Data'!$D$6:$D$445,$A6,'Revenue Data'!$B$6:$B$445,DATE(2025,1,1)) -> 155148.9 | D6: =SUMIFS('Revenue Data'!$I$6:$I$445,'Revenue Data'!$D$6:$D$445,$A6,'Revenue Data'!$B$6:$B$445,DATE(2025,2,1)) -> 164757.65 | E6: =SUMIFS('Revenue Data'!$I$6:$I$445,'Revenue Data'!$D$6:$D$445,$A6,'Revenue Data'!$B$6:$B$445,DATE(2025,3,1)) -> 368537.89 | F6: =SUMIFS('Revenue Data'!$I$6:$I$445,'Revenue Data'!$D$6:$D$445,$A6,'Revenue Data'!$B$6:$B$445,DATE(2025,4,1)) -> 336868.02 | G6: =SUMIFS('Revenue Data'!$I$6:$I$445,'Revenue Data'!$D$6:$D$445,$A6,'Revenue Data'!$B$6:$B$445,DATE(2025,5,1)) -> 332456.63 | H6: =SUMIFS('Revenue Data'!$I$6:$I$445,'Revenue Data'!$D$6:$D$445,$A6,'Revenue Data'!$B$6:$B$445,DATE(2025,6,1)) -> 350458.47 | I6: =SUMIFS('Revenue Data'!$I$6:$I$445,'Revenue Data'!$D$6:$D$445,$A6,'Revenue Data'!$B$6:$B$445,DATE(2025,7,1)) -> 340232.14 | J6: =SUMIFS('Revenue Data'!$I$6:$I$445,'Revenue Data'!$D$6:$D$445,$A6,'Revenue Data'!$B$6:$B$445,DATE(2025,8,1)) -> 336440.26 | K6: =SUMIFS('Revenue Data'!$I$6:$I$445,'Revenue Data'!$D$6:$D$445,$A6,'Revenue Data'!$B$6:$B$445,DATE(2025,9,1)) -> 363801.22 | L6: =SUMIFS('Revenue Data'!$I$6:$I$445,'Revenue Data'!$D$6:$D$445,$A6,'Revenue Data'!$B$6:$B$445,DATE(2025,10,1)) -> 335257.47 | M6: =SUMIFS('Revenue Data'!$I$6:$I$445,'Revenue Data'!$D$6:$D$445,$A6,'Revenue Data'!$B$6:$B$445,DATE(2025,11,1)) -> 341781.4 | N6: =SUMIFS('Revenue Data'!$I$6:$I$445,'Revenue Data'!$D$6:$D$445,$A6,'Revenue Data'!$B$6:$B$445,DATE(2025,12,1)) -> 319641.45 | O6: =SUMIFS('Revenue Data'!$I$6:$I$445,'Revenue Data'!$D$6:$D$445,$A6,'Revenue Data'!$B$6:$B$445,DATE(2026,1,1)) -> 318284.01 | P6: =SUMIFS('Revenue Data'!$I$6:$I$445,'Revenue Data'!$D$6:$D$445,$A6,'Revenue Data'!$B$6:$B$445,DATE(2026,2,1)) -> 324264.98 | Q6: =SUMIFS('Revenue Data'!$I$6:$I$445,'Revenue Data'!$D$6:$D$445,$A6,'Revenue Data'!$B$6:$B$445,DATE(2026,3,1)) -> 356696.43 | R6: =SUMIFS('Revenue Data'!$I$6:$I$445,'Revenue Data'!$D$6:$D$445,$A6,'Revenue Data'!$B$6:$B$445,DATE(2026,4,1)) -> 327002.92 | S6: =SUMIFS('Revenue Data'!$I$6:$I$445,'Revenue Data'!$D$6:$D$445,$A6,'Revenue Data'!$B$6:$B$445,DATE(2026,5,1)) -> 356192.97 | T6: =SUMIFS('Revenue Data'!$I$6:$I$445,'Revenue Data'!$D$6:$D$445,$A6,'Revenue Data'!$B$6:$B$445,DATE(2026,6,1)) -> 359767.17 | U6: =SUMIFS('Revenue Data'!$I$6:$I$445,'Revenue Data'!$D$6:$D$445,$A6,'Revenue Data'!$B$6:$B$445,DATE(2026,7,1)) -> 324386.27 | V6: =SUMIFS('Revenue Data'!$I$6:$I$445,'Revenue Data'!$D$6:$D$445,$A6,'Revenue Data'!$B$6:$B$445,DATE(2026,8,1)) -> 317472.93 | W6: =SUMIFS('Revenue Data'!$I$6:$I$445,'Revenue Data'!$D$6:$D$445,$A6,'Revenue Data'!$B$6:$B$445,DATE(2026,9,1)) -> 336166.56 | X6: =SUM(C6:N6) -> 3745381.5 | Y6: =SUM(O6:W6) -> 3020234.2
A7: ACC-1002 | B7: Fabrikam Health | C7: =SUMIFS('Revenue Data'!$I$6:$I$445,'Revenue Data'!$D$6:$D$445,$A7,'Revenue Data'!$B$6:$B$445,DATE(2025,1,1)) -> 49181.04 | D7: =SUMIFS('Revenue Data'!$I$6:$I$445,'Revenue Data'!$D$6:$D$445,$A7,'Revenue Data'!$B$6:$B$445,DATE(2025,2,1)) -> 49394.74 | E7: =SUMIFS('Revenue Data'!$I$6:$I$445,'Revenue Data'!$D$6:$D$445,$A7,'Revenue Data'!$B$6:$B$445,DATE(2025,3,1)) -> 51195.22 | F7: =SUMIFS('Revenue Data'!$I$6:$I$445,'Revenue Data'!$D$6:$D$445,$A7,'Revenue Data'!$B$6:$B$445,DATE(2025,4,1)) -> 50037.73 | G7: =SUMIFS('Revenue Data'!$I$6:$I$445,'Revenue Data'!$D$6:$D$445,$A7,'Revenue Data'!$B$6:$B$445,DATE(2025,5,1)) -> 49128.58 | H7: =SUMIFS('Revenue Data'!$I$6:$I$445,'Revenue Data'!$D$6:$D$445,$A7,'Revenue Data'!$B$6:$B$445,DATE(2025,6,1)) -> 52468.87 | I7: =SUMIFS('Revenue Data'!$I$6:$I$445,'Revenue Data'!$D$6:$D$445,$A7,'Revenue Data'!$B$6:$B$445,DATE(2025,7,1)) -> 45367.76 | J7: =SUMIFS('Revenue Data'!$I$6:$I$445,'Revenue Data'!$D$6:$D$445,$A7,'Revenue Data'!$B$6:$B$445,DATE(2025,8,1)) -> 50542.07 | K7: =SUMIFS('Revenue Data'!$I$6:$I$445,'Revenue Data'!$D$6:$D$445,$A7,'Revenue Data'!$B$6:$B$445,DATE(2025,9,1)) -> 129931.12 | L7: =SUMIFS('Revenue Data'!$I$6:$I$445,'Revenue Data'!$D$6:$D$445,$A7,'Revenue Data'!$B$6:$B$445,DATE(2025,10,1)) -> 124376.04 | M7: =SUMIFS('Revenue Data'!$I$6:$I$445,'Revenue Data'!$D$6:$D$445,$A7,'Revenue Data'!$B$6:$B$445,DATE(2025,11,1)) -> 122144.05 | N7: =SUMIFS('Revenue Data'!$I$6:$I$445,'Revenue Data'!$D$6:$D$445,$A7,'Revenue Data'!$B$6:$B$445,DATE(2025,12,1)) -> 115064.36 | O7: =SUMIFS('Revenue Data'!$I$6:$I$445,'Revenue Data'!$D$6:$D$445,$A7,'Revenue Data'!$B$6:$B$445,DATE(2026,1,1)) -> 165284 | P7: =SUMIFS('Revenue Data'!$I$6:$I$445,'Revenue Data'!$D$6:$D$445,$A7,'Revenue Data'!$B$6:$B$445,DATE(2026,2,1)) -> 178409.72 | Q7: =SUMIFS('Revenue Data'!$I$6:$I$445,'Revenue Data'!$D$6:$D$445,$A7,'Revenue Data'!$B$6:$B$445,DATE(2026,3,1)) -> 187426.87 | R7: =SUMIFS('Revenue Data'!$I$6:$I$445,'Revenue Data'!$D$6:$D$445,$A7,'Revenue Data'!$B$6:$B$445,DATE(2026,4,1)) -> 172659.16 | S7: =SUMIFS('Revenue Data'!$I$6:$I$445,'Revenue Data'!$D$6:$D$445,$A7,'Revenue Data'!$B$6:$B$445,DATE(2026,5,1)) -> 179038.71 | T7: =SUMIFS('Revenue Data'!$I$6:$I$445,'Revenue Data'!$D$6:$D$445,$A7,'Revenue Data'!$B$6:$B$445,DATE(2026,6,1)) -> 182212.6 | U7: =SUMIFS('Revenue Data'!$I$6:$I$445,'Revenue Data'!$D$6:$D$445,$A7,'Revenue Data'!$B$6:$B$445,DATE(2026,7,1)) -> 173928.44 | V7: =SUMIFS('Revenue Data'!$I$6:$I$445,'Revenue Data'!$D$6:$D$445,$A7,'Revenue Data'!$B$6:$B$445,DATE(2026,8,1)) -> 185490.86 | W7: =SUMIFS('Revenue Data'!$I$6:$I$445,'Revenue Data'!$D$6:$D$445,$A7,'Revenue Data'!$B$6:$B$445,DATE(2026,9,1)) -> 188701.19 | X7: =SUM(C7:N7) -> 888831.58 | Y7: =SUM(O7:W7) -> 1613151.6
A8: ACC-1003 | B8: Woodgrove Bank | C8: =SUMIFS('Revenue Data'!$I$6:$I$445,'Revenue Data'!$D$6:$D$445,$A8,'Revenue Data'!$B$6:$B$445,DATE(2025,1,1)) -> 75388.12 | D8: =SUMIFS('Revenue Data'!$I$6:$I$445,'Revenue Data'!$D$6:$D$445,$A8,'Revenue Data'!$B$6:$B$445,DATE(2025,2,1)) -> 78728.82 | E8: =SUMIFS('Revenue Data'!$I$6:$I$445,'Revenue Data'!$D$6:$D$445,$A8,'Revenue Data'!$B$6:$B$445,DATE(2025,3,1)) -> 78572.35 | F8: =SUMIFS('Revenue Data'!$I$6:$I$445,'Revenue Data'!$D$6:$D$445,$A8,'Revenue Data'!$B$6:$B$445,DATE(2025,4,1)) -> 75186.1 | G8: =SUMIFS('Revenue Data'!$I$6:$I$445,'Revenue Data'!$D$6:$D$445,$A8,'Revenue Data'!$B$6:$B$445,DATE(2025,5,1)) -> 81209.6 | H8: =SUMIFS('Revenue Data'!$I$6:$I$445,'Revenue Data'!$D$6:$D$445,$A8,'Revenue Data'!$B$6:$B$445,DATE(2025,6,1)) -> 83031.02 | I8: =SUMIFS('Revenue Data'!$I$6:$I$445,'Revenue Data'!$D$6:$D$445,$A8,'Revenue Data'!$B$6:$B$445,DATE(2025,7,1)) -> 79290.31 | J8: =SUMIFS('Revenue Data'!$I$6:$I$445,'Revenue Data'!$D$6:$D$445,$A8,'Revenue Data'!$B$6:$B$445,DATE(2025,8,1)) -> 76766.36 | K8: =SUMIFS('Revenue Data'!$I$6:$I$445,'Revenue Data'!$D$6:$D$445,$A8,'Revenue Data'!$B$6:$B$445,DATE(2025,9,1)) -> 82112.09 | L8: =SUMIFS('Revenue Data'!$I$6:$I$445,'Revenue Data'!$D$6:$D$445,$A8,'Revenue Data'!$B$6:$B$445,DATE(2025,10,1)) -> 79215.2 | M8: =SUMIFS('Revenue Data'!$I$6:$I$445,'Revenue Data'!$D$6:$D$445,$A8,'Revenue Data'!$B$6:$B$445,DATE(2025,11,1)) -> 80302.33 | N8: =SUMIFS('Revenue Data'!$I$6:$I$445,'Revenue Data'!$D$6:$D$445,$A8,'Revenue Data'!$B$6:$B$445,DATE(2025,12,1)) -> 73347.58 | O8: =SUMIFS('Revenue Data'!$I$6:$I$445,'Revenue Data'!$D$6:$D$445,$A8,'Revenue Data'!$B$6:$B$445,DATE(2026,1,1)) -> 86131.66 | P8: =SUMIFS('Revenue Data'!$I$6:$I$445,'Revenue Data'!$D$6:$D$445,$A8,'Revenue Data'!$B$6:$B$445,DATE(2026,2,1)) -> 84197.37 | Q8: =SUMIFS('Revenue Data'!$I$6:$I$445,'Revenue Data'!$D$6:$D$445,$A8,'Revenue Data'!$B$6:$B$445,DATE(2026,3,1)) -> 90685.65 | R8: =SUMIFS('Revenue Data'!$I$6:$I$445,'Revenue Data'!$D$6:$D$445,$A8,'Revenue Data'!$B$6:$B$445,DATE(2026,4,1)) -> 82668.6 | S8: =SUMIFS('Revenue Data'!$I$6:$I$445,'Revenue Data'!$D$6:$D$445,$A8,'Revenue Data'!$B$6:$B$445,DATE(2026,5,1)) -> 88697.94 | T8: =SUMIFS('Revenue Data'!$I$6:$I$445,'Revenue Data'!$D$6:$D$445,$A8,'Revenue Data'!$B$6:$B$445,DATE(2026,6,1)) -> 88629.27 | U8: =SUMIFS('Revenue Data'!$I$6:$I$445,'Revenue Data'!$D$6:$D$445,$A8,'Revenue Data'!$B$6:$B$445,DATE(2026,7,1)) -> 83536.63 | V8: =SUMIFS('Revenue Data'!$I$6:$I$445,'Revenue Data'!$D$6:$D$445,$A8,'Revenue Data'!$B$6:$B$445,DATE(2026,8,1)) -> 139055.14 | W8: =SUMIFS('Revenue Data'!$I$6:$I$445,'Revenue Data'!$D$6:$D$445,$A8,'Revenue Data'!$B$6:$B$445,DATE(2026,9,1)) -> 140181.33 | X8: =SUM(C8:N8) -> 943149.88 | Y8: =SUM(O8:W8) -> 883783.59
A9: ACC-1004 | B9: Tailspin Airlines | C9: =SUMIFS('Revenue Data'!$I$6:$I$445,'Revenue Data'!$D$6:$D$445,$A9,'Revenue Data'!$B$6:$B$445,DATE(2025,1,1)) -> 134945.86 | D9: =SUMIFS('Revenue Data'!$I$6:$I$445,'Revenue Data'!$D$6:$D$445,$A9,'Revenue Data'!$B$6:$B$445,DATE(2025,2,1)) -> 141901.61 | E9: =SUMIFS('Revenue Data'!$I$6:$I$445,'Revenue Data'!$D$6:$D$445,$A9,'Revenue Data'!$B$6:$B$445,DATE(2025,3,1)) -> 151114.65 | F9: =SUMIFS('Revenue Data'!$I$6:$I$445,'Revenue Data'!$D$6:$D$445,$A9,'Revenue Data'!$B$6:$B$445,DATE(2025,4,1)) -> 138096.48 | G9: =SUMIFS('Revenue Data'!$I$6:$I$445,'Revenue Data'!$D$6:$D$445,$A9,'Revenue Data'!$B$6:$B$445,DATE(2025,5,1)) -> 142328.97 | H9: =SUMIFS('Revenue Data'!$I$6:$I$445,'Revenue Data'!$D$6:$D$445,$A9,'Revenue Data'!$B$6:$B$445,DATE(2025,6,1)) -> 141171.28 | I9: =SUMIFS('Revenue Data'!$I$6:$I$445,'Revenue Data'!$D$6:$D$445,$A9,'Revenue Data'!$B$6:$B$445,DATE(2025,7,1)) -> 145630.03 | J9: =SUMIFS('Revenue Data'!$I$6:$I$445,'Revenue Data'!$D$6:$D$445,$A9,'Revenue Data'!$B$6:$B$445,DATE(2025,8,1)) -> 145773.21 | K9: =SUMIFS('Revenue Data'!$I$6:$I$445,'Revenue Data'!$D$6:$D$445,$A9,'Revenue Data'!$B$6:$B$445,DATE(2025,9,1)) -> 147650.44 | L9: =SUMIFS('Revenue Data'!$I$6:$I$445,'Revenue Data'!$D$6:$D$445,$A9,'Revenue Data'!$B$6:$B$445,DATE(2025,10,1)) -> 141058.85 | M9: =SUMIFS('Revenue Data'!$I$6:$I$445,'Revenue Data'!$D$6:$D$445,$A9,'Revenue Data'!$B$6:$B$445,DATE(2025,11,1)) -> 141309.22 | N9: =SUMIFS('Revenue Data'!$I$6:$I$445,'Revenue Data'!$D$6:$D$445,$A9,'Revenue Data'!$B$6:$B$445,DATE(2025,12,1)) -> 128422.68 | O9: =SUMIFS('Revenue Data'!$I$6:$I$445,'Revenue Data'!$D$6:$D$445,$A9,'Revenue Data'!$B$6:$B$445,DATE(2026,1,1)) -> 152291.19 | P9: =SUMIFS('Revenue Data'!$I$6:$I$445,'Revenue Data'!$D$6:$D$445,$A9,'Revenue Data'!$B$6:$B$445,DATE(2026,2,1)) -> 160202.23 | Q9: =SUMIFS('Revenue Data'!$I$6:$I$445,'Revenue Data'!$D$6:$D$445,$A9,'Revenue Data'!$B$6:$B$445,DATE(2026,3,1)) -> 170327.74 | R9: =SUMIFS('Revenue Data'!$I$6:$I$445,'Revenue Data'!$D$6:$D$445,$A9,'Revenue Data'!$B$6:$B$445,DATE(2026,4,1)) -> 160995.56 | S9: =SUMIFS('Revenue Data'!$I$6:$I$445,'Revenue Data'!$D$6:$D$445,$A9,'Revenue Data'!$B$6:$B$445,DATE(2026,5,1)) -> 168273.55 | T9: =SUMIFS('Revenue Data'!$I$6:$I$445,'Revenue Data'!$D$6:$D$445,$A9,'Revenue Data'!$B$6:$B$445,DATE(2026,6,1)) -> 172203.38 | U9: =SUMIFS('Revenue Data'!$I$6:$I$445,'Revenue Data'!$D$6:$D$445,$A9,'Revenue Data'!$B$6:$B$445,DATE(2026,7,1)) -> 157281.39 | V9: =SUMIFS('Revenue Data'!$I$6:$I$445,'Revenue Data'!$D$6:$D$445,$A9,'Revenue Data'!$B$6:$B$445,DATE(2026,8,1)) -> 163916.33 | W9: =SUMIFS('Revenue Data'!$I$6:$I$445,'Revenue Data'!$D$6:$D$445,$A9,'Revenue Data'!$B$6:$B$445,DATE(2026,9,1)) -> 175244.45 | X9: =SUM(C9:N9) -> 1699403.3 | Y9: =SUM(O9:W9) -> 1480735.8
A10: ACC-1005 | B10: Litware Insurance | C10: =SUMIFS('Revenue Data'!$I$6:$I$445,'Revenue Data'!$D$6:$D$445,$A10,'Revenue Data'!$B$6:$B$445,DATE(2025,1,1)) -> 22547.56 | D10: =SUMIFS('Revenue Data'!$I$6:$I$445,'Revenue Data'!$D$6:$D$445,$A10,'Revenue Data'!$B$6:$B$445,DATE(2025,2,1)) -> 24369.69 | E10: =SUMIFS('Revenue Data'!$I$6:$I$445,'Revenue Data'!$D$6:$D$445,$A10,'Revenue Data'!$B$6:$B$445,DATE(2025,3,1)) -> 26921.81 | F10: =SUMIFS('Revenue Data'!$I$6:$I$445,'Revenue Data'!$D$6:$D$445,$A10,'Revenue Data'!$B$6:$B$445,DATE(2025,4,1)) -> 24126.41 | G10: =SUMIFS('Revenue Data'!$I$6:$I$445,'Revenue Data'!$D$6:$D$445,$A10,'Revenue Data'!$B$6:$B$445,DATE(2025,5,1)) -> 24949.03 | H10: =SUMIFS('Revenue Data'!$I$6:$I$445,'Revenue Data'!$D$6:$D$445,$A10,'Revenue Data'!$B$6:$B$445,DATE(2025,6,1)) -> 25684.68 | I10: =SUMIFS('Revenue Data'!$I$6:$I$445,'Revenue Data'!$D$6:$D$445,$A10,'Revenue Data'!$B$6:$B$445,DATE(2025,7,1)) -> 22400.81 | J10: =SUMIFS('Revenue Data'!$I$6:$I$445,'Revenue Data'!$D$6:$D$445,$A10,'Revenue Data'!$B$6:$B$445,DATE(2025,8,1)) -> 25353.44 | K10: =SUMIFS('Revenue Data'!$I$6:$I$445,'Revenue Data'!$D$6:$D$445,$A10,'Revenue Data'!$B$6:$B$445,DATE(2025,9,1)) -> 25416.13 | L10: =SUMIFS('Revenue Data'!$I$6:$I$445,'Revenue Data'!$D$6:$D$445,$A10,'Revenue Data'!$B$6:$B$445,DATE(2025,10,1)) -> 24485.93 | M10: =SUMIFS('Revenue Data'!$I$6:$I$445,'Revenue Data'!$D$6:$D$445,$A10,'Revenue Data'!$B$6:$B$445,DATE(2025,11,1)) -> 24607.81 | N10: =SUMIFS('Revenue Data'!$I$6:$I$445,'Revenue Data'!$D$6:$D$445,$A10,'Revenue Data'!$B$6:$B$445,DATE(2025,12,1)) -> 22274.63 | O10: =SUMIFS('Revenue Data'!$I$6:$I$445,'Revenue Data'!$D$6:$D$445,$A10,'Revenue Data'!$B$6:$B$445,DATE(2026,1,1)) -> 27372.84 | P10: =SUMIFS('Revenue Data'!$I$6:$I$445,'Revenue Data'!$D$6:$D$445,$A10,'Revenue Data'!$B$6:$B$445,DATE(2026,2,1)) -> 26976.11 | Q10: =SUMIFS('Revenue Data'!$I$6:$I$445,'Revenue Data'!$D$6:$D$445,$A10,'Revenue Data'!$B$6:$B$445,DATE(2026,3,1)) -> 29109.71 | R10: =SUMIFS('Revenue Data'!$I$6:$I$445,'Revenue Data'!$D$6:$D$445,$A10,'Revenue Data'!$B$6:$B$445,DATE(2026,4,1)) -> 29137.89 | S10: =SUMIFS('Revenue Data'!$I$6:$I$445,'Revenue Data'!$D$6:$D$445,$A10,'Revenue Data'!$B$6:$B$445,DATE(2026,5,1)) -> 30191.24 | T10: =SUMIFS('Revenue Data'!$I$6:$I$445,'Revenue Data'!$D$6:$D$445,$A10,'Revenue Data'!$B$6:$B$445,DATE(2026,6,1)) -> 29711.14 | U10: =SUMIFS('Revenue Data'!$I$6:$I$445,'Revenue Data'!$D$6:$D$445,$A10,'Revenue Data'!$B$6:$B$445,DATE(2026,7,1)) -> 28633.95 | V10: =SUMIFS('Revenue Data'!$I$6:$I$445,'Revenue Data'!$D$6:$D$445,$A10,'Revenue Data'!$B$6:$B$445,DATE(2026,8,1)) -> 26852.21 | W10: =SUMIFS('Revenue Data'!$I$6:$I$445,'Revenue Data'!$D$6:$D$445,$A10,'Revenue Data'!$B$6:$B$445,DATE(2026,9,1)) -> 29976.21 | X10: =SUM(C10:N10) -> 293137.93 | Y10: =SUM(O10:W10) -> 257961.3
A11: ACC-1006 | B11: Contoso Manufacturing | C11: =SUMIFS('Revenue Data'!$I$6:$I$445,'Revenue Data'!$D$6:$D$445,$A11,'Revenue Data'!$B$6:$B$445,DATE(2025,1,1)) -> 106038.01 | D11: =SUMIFS('Revenue Data'!$I$6:$I$445,'Revenue Data'!$D$6:$D$445,$A11,'Revenue Data'!$B$6:$B$445,DATE(2025,2,1)) -> 112013.29 | E11: =SUMIFS('Revenue Data'!$I$6:$I$445,'Revenue Data'!$D$6:$D$445,$A11,'Revenue Data'!$B$6:$B$445,DATE(2025,3,1)) -> 124795.94 | F11: =SUMIFS('Revenue Data'!$I$6:$I$445,'Revenue Data'!$D$6:$D$445,$A11,'Revenue Data'!$B$6:$B$445,DATE(2025,4,1)) -> 115426.42 | G11: =SUMIFS('Revenue Data'!$I$6:$I$445,'Revenue Data'!$D$6:$D$445,$A11,'Revenue Data'!$B$6:$B$445,DATE(2025,5,1)) -> 120338.63 | H11: =SUMIFS('Revenue Data'!$I$6:$I$445,'Revenue Data'!$D$6:$D$445,$A11,'Revenue Data'!$B$6:$B$445,DATE(2025,6,1)) -> 121984.19 | I11: =SUMIFS('Revenue Data'!$I$6:$I$445,'Revenue Data'!$D$6:$D$445,$A11,'Revenue Data'!$B$6:$B$445,DATE(2025,7,1)) -> 116796.3 | J11: =SUMIFS('Revenue Data'!$I$6:$I$445,'Revenue Data'!$D$6:$D$445,$A11,'Revenue Data'!$B$6:$B$445,DATE(2025,8,1)) -> 113393.95 | K11: =SUMIFS('Revenue Data'!$I$6:$I$445,'Revenue Data'!$D$6:$D$445,$A11,'Revenue Data'!$B$6:$B$445,DATE(2025,9,1)) -> 126189.6 | L11: =SUMIFS('Revenue Data'!$I$6:$I$445,'Revenue Data'!$D$6:$D$445,$A11,'Revenue Data'!$B$6:$B$445,DATE(2025,10,1)) -> 113256.72 | M11: =SUMIFS('Revenue Data'!$I$6:$I$445,'Revenue Data'!$D$6:$D$445,$A11,'Revenue Data'!$B$6:$B$445,DATE(2025,11,1)) -> 118182.56 | N11: =SUMIFS('Revenue Data'!$I$6:$I$445,'Revenue Data'!$D$6:$D$445,$A11,'Revenue Data'!$B$6:$B$445,DATE(2025,12,1)) -> 104894.64 | O11: =SUMIFS('Revenue Data'!$I$6:$I$445,'Revenue Data'!$D$6:$D$445,$A11,'Revenue Data'!$B$6:$B$445,DATE(2026,1,1)) -> 100570.4 | P11: =SUMIFS('Revenue Data'!$I$6:$I$445,'Revenue Data'!$D$6:$D$445,$A11,'Revenue Data'!$B$6:$B$445,DATE(2026,2,1)) -> 107965.82 | Q11: =SUMIFS('Revenue Data'!$I$6:$I$445,'Revenue Data'!$D$6:$D$445,$A11,'Revenue Data'!$B$6:$B$445,DATE(2026,3,1)) -> 110820.88 | R11: =SUMIFS('Revenue Data'!$I$6:$I$445,'Revenue Data'!$D$6:$D$445,$A11,'Revenue Data'!$B$6:$B$445,DATE(2026,4,1)) -> 108471.83 | S11: =SUMIFS('Revenue Data'!$I$6:$I$445,'Revenue Data'!$D$6:$D$445,$A11,'Revenue Data'!$B$6:$B$445,DATE(2026,5,1)) -> 114238.53 | T11: =SUMIFS('Revenue Data'!$I$6:$I$445,'Revenue Data'!$D$6:$D$445,$A11,'Revenue Data'!$B$6:$B$445,DATE(2026,6,1)) -> 116025.63 | U11: =SUMIFS('Revenue Data'!$I$6:$I$445,'Revenue Data'!$D$6:$D$445,$A11,'Revenue Data'!$B$6:$B$445,DATE(2026,7,1)) -> 108938.36 | V11: =SUMIFS('Revenue Data'!$I$6:$I$445,'Revenue Data'!$D$6:$D$445,$A11,'Revenue Data'!$B$6:$B$445,DATE(2026,8,1)) -> 103925.72 | W11: =SUMIFS('Revenue Data'!$I$6:$I$445,'Revenue Data'!$D$6:$D$445,$A11,'Revenue Data'!$B$6:$B$445,DATE(2026,9,1)) -> 112656.41 | X11: =SUM(C11:N11) -> 1393310.2 | Y11: =SUM(O11:W11) -> 983613.58
A12: ACC-1007 | B12: Adventure Works Retail | C12: =SUMIFS('Revenue Data'!$I$6:$I$445,'Revenue Data'!$D$6:$D$445,$A12,'Revenue Data'!$B$6:$B$445,DATE(2025,1,1)) -> 45089.13 | D12: =SUMIFS('Revenue Data'!$I$6:$I$445,'Revenue Data'!$D$6:$D$445,$A12,'Revenue Data'!$B$6:$B$445,DATE(2025,2,1)) -> 51234.47 | E12: =SUMIFS('Revenue Data'!$I$6:$I$445,'Revenue Data'!$D$6:$D$445,$A12,'Revenue Data'!$B$6:$B$445,DATE(2025,3,1)) -> 52680.63 | F12: =SUMIFS('Revenue Data'!$I$6:$I$445,'Revenue Data'!$D$6:$D$445,$A12,'Revenue Data'!$B$6:$B$445,DATE(2025,4,1)) -> 46667.92 | G12: =SUMIFS('Revenue Data'!$I$6:$I$445,'Revenue Data'!$D$6:$D$445,$A12,'Revenue Data'!$B$6:$B$445,DATE(2025,5,1)) -> 47897.9 | H12: =SUMIFS('Revenue Data'!$I$6:$I$445,'Revenue Data'!$D$6:$D$445,$A12,'Revenue Data'!$B$6:$B$445,DATE(2025,6,1)) -> 51584.91 | I12: =SUMIFS('Revenue Data'!$I$6:$I$445,'Revenue Data'!$D$6:$D$445,$A12,'Revenue Data'!$B$6:$B$445,DATE(2025,7,1)) -> 46887.9 | J12: =SUMIFS('Revenue Data'!$I$6:$I$445,'Revenue Data'!$D$6:$D$445,$A12,'Revenue Data'!$B$6:$B$445,DATE(2025,8,1)) -> 51136.6 | K12: =SUMIFS('Revenue Data'!$I$6:$I$445,'Revenue Data'!$D$6:$D$445,$A12,'Revenue Data'!$B$6:$B$445,DATE(2025,9,1)) -> 50971.59 | L12: =SUMIFS('Revenue Data'!$I$6:$I$445,'Revenue Data'!$D$6:$D$445,$A12,'Revenue Data'!$B$6:$B$445,DATE(2025,10,1)) -> 50945.89 | M12: =SUMIFS('Revenue Data'!$I$6:$I$445,'Revenue Data'!$D$6:$D$445,$A12,'Revenue Data'!$B$6:$B$445,DATE(2025,11,1)) -> 48695.52 | N12: =SUMIFS('Revenue Data'!$I$6:$I$445,'Revenue Data'!$D$6:$D$445,$A12,'Revenue Data'!$B$6:$B$445,DATE(2025,12,1)) -> 47654.19 | O12: =SUMIFS('Revenue Data'!$I$6:$I$445,'Revenue Data'!$D$6:$D$445,$A12,'Revenue Data'!$B$6:$B$445,DATE(2026,1,1)) -> 53610.17 | P12: =SUMIFS('Revenue Data'!$I$6:$I$445,'Revenue Data'!$D$6:$D$445,$A12,'Revenue Data'!$B$6:$B$445,DATE(2026,2,1)) -> 56447.35 | Q12: =SUMIFS('Revenue Data'!$I$6:$I$445,'Revenue Data'!$D$6:$D$445,$A12,'Revenue Data'!$B$6:$B$445,DATE(2026,3,1)) -> 56941.25 | R12: =SUMIFS('Revenue Data'!$I$6:$I$445,'Revenue Data'!$D$6:$D$445,$A12,'Revenue Data'!$B$6:$B$445,DATE(2026,4,1)) -> 58974.98 | S12: =SUMIFS('Revenue Data'!$I$6:$I$445,'Revenue Data'!$D$6:$D$445,$A12,'Revenue Data'!$B$6:$B$445,DATE(2026,5,1)) -> 59640.23 | T12: =SUMIFS('Revenue Data'!$I$6:$I$445,'Revenue Data'!$D$6:$D$445,$A12,'Revenue Data'!$B$6:$B$445,DATE(2026,6,1)) -> 61298.96 | U12: =SUMIFS('Revenue Data'!$I$6:$I$445,'Revenue Data'!$D$6:$D$445,$A12,'Revenue Data'!$B$6:$B$445,DATE(2026,7,1)) -> 58082.83 | V12: =SUMIFS('Revenue Data'!$I$6:$I$445,'Revenue Data'!$D$6:$D$445,$A12,'Revenue Data'!$B$6:$B$445,DATE(2026,8,1)) -> 60120.29 | W12: =SUMIFS('Revenue Data'!$I$6:$I$445,'Revenue Data'!$D$6:$D$445,$A12,'Revenue Data'!$B$6:$B$445,DATE(2026,9,1)) -> 61809.8 | X12: =SUM(C12:N12) -> 591446.65 | Y12: =SUM(O12:W12) -> 526925.86
A13: ACC-1008 | B13: Wingtip Logistics | C13: =SUMIFS('Revenue Data'!$I$6:$I$445,'Revenue Data'!$D$6:$D$445,$A13,'Revenue Data'!$B$6:$B$445,DATE(2025,1,1)) -> 15049.28 | D13: =SUMIFS('Revenue Data'!$I$6:$I$445,'Revenue Data'!$D$6:$D$445,$A13,'Revenue Data'!$B$6:$B$445,DATE(2025,2,1)) -> 16504.81 | E13: =SUMIFS('Revenue Data'!$I$6:$I$445,'Revenue Data'!$D$6:$D$445,$A13,'Revenue Data'!$B$6:$B$445,DATE(2025,3,1)) -> 17691.59 | F13: =SUMIFS('Revenue Data'!$I$6:$I$445,'Revenue Data'!$D$6:$D$445,$A13,'Revenue Data'!$B$6:$B$445,DATE(2025,4,1)) -> 16448.59 | G13: =SUMIFS('Revenue Data'!$I$6:$I$445,'Revenue Data'!$D$6:$D$445,$A13,'Revenue Data'!$B$6:$B$445,DATE(2025,5,1)) -> 16043.37 | H13: =SUMIFS('Revenue Data'!$I$6:$I$445,'Revenue Data'!$D$6:$D$445,$A13,'Revenue Data'!$B$6:$B$445,DATE(2025,6,1)) -> 93942.96 | I13: =SUMIFS('Revenue Data'!$I$6:$I$445,'Revenue Data'!$D$6:$D$445,$A13,'Revenue Data'!$B$6:$B$445,DATE(2025,7,1)) -> 85107.65 | J13: =SUMIFS('Revenue Data'!$I$6:$I$445,'Revenue Data'!$D$6:$D$445,$A13,'Revenue Data'!$B$6:$B$445,DATE(2025,8,1)) -> 87669.91 | K13: =SUMIFS('Revenue Data'!$I$6:$I$445,'Revenue Data'!$D$6:$D$445,$A13,'Revenue Data'!$B$6:$B$445,DATE(2025,9,1)) -> 96399.73 | L13: =SUMIFS('Revenue Data'!$I$6:$I$445,'Revenue Data'!$D$6:$D$445,$A13,'Revenue Data'!$B$6:$B$445,DATE(2025,10,1)) -> 92072.11 | M13: =SUMIFS('Revenue Data'!$I$6:$I$445,'Revenue Data'!$D$6:$D$445,$A13,'Revenue Data'!$B$6:$B$445,DATE(2025,11,1)) -> 89115.7 | N13: =SUMIFS('Revenue Data'!$I$6:$I$445,'Revenue Data'!$D$6:$D$445,$A13,'Revenue Data'!$B$6:$B$445,DATE(2025,12,1)) -> 81373.52 | O13: =SUMIFS('Revenue Data'!$I$6:$I$445,'Revenue Data'!$D$6:$D$445,$A13,'Revenue Data'!$B$6:$B$445,DATE(2026,1,1)) -> 143416.95 | P13: =SUMIFS('Revenue Data'!$I$6:$I$445,'Revenue Data'!$D$6:$D$445,$A13,'Revenue Data'!$B$6:$B$445,DATE(2026,2,1)) -> 144607.92 | Q13: =SUMIFS('Revenue Data'!$I$6:$I$445,'Revenue Data'!$D$6:$D$445,$A13,'Revenue Data'!$B$6:$B$445,DATE(2026,3,1)) -> 153514.45 | R13: =SUMIFS('Revenue Data'!$I$6:$I$445,'Revenue Data'!$D$6:$D$445,$A13,'Revenue Data'!$B$6:$B$445,DATE(2026,4,1)) -> 146948.72 | S13: =SUMIFS('Revenue Data'!$I$6:$I$445,'Revenue Data'!$D$6:$D$445,$A13,'Revenue Data'!$B$6:$B$445,DATE(2026,5,1)) -> 145604.14 | T13: =SUMIFS('Revenue Data'!$I$6:$I$445,'Revenue Data'!$D$6:$D$445,$A13,'Revenue Data'!$B$6:$B$445,DATE(2026,6,1)) -> 155394.89 | U13: =SUMIFS('Revenue Data'!$I$6:$I$445,'Revenue Data'!$D$6:$D$445,$A13,'Revenue Data'!$B$6:$B$445,DATE(2026,7,1)) -> 137121.67 | V13: =SUMIFS('Revenue Data'!$I$6:$I$445,'Revenue Data'!$D$6:$D$445,$A13,'Revenue Data'!$B$6:$B$445,DATE(2026,8,1)) -> 148536.55 | W13: =SUMIFS('Revenue Data'!$I$6:$I$445,'Revenue Data'!$D$6:$D$445,$A13,'Revenue Data'!$B$6:$B$445,DATE(2026,9,1)) -> 154763.4 | X13: =SUM(C13:N13) -> 707419.22 | Y13: =SUM(O13:W13) -> 1329908.7
A14: ACC-1009 | B14: Relecloud | C14: =SUMIFS('Revenue Data'!$I$6:$I$445,'Revenue Data'!$D$6:$D$445,$A14,'Revenue Data'!$B$6:$B$445,DATE(2025,1,1)) -> 177071.91 | D14: =SUMIFS('Revenue Data'!$I$6:$I$445,'Revenue Data'!$D$6:$D$445,$A14,'Revenue Data'!$B$6:$B$445,DATE(2025,2,1)) -> 166668.33 | E14: =SUMIFS('Revenue Data'!$I$6:$I$445,'Revenue Data'!$D$6:$D$445,$A14,'Revenue Data'!$B$6:$B$445,DATE(2025,3,1)) -> 186547.89 | F14: =SUMIFS('Revenue Data'!$I$6:$I$445,'Revenue Data'!$D$6:$D$445,$A14,'Revenue Data'!$B$6:$B$445,DATE(2025,4,1)) -> 183602.2 | G14: =SUMIFS('Revenue Data'!$I$6:$I$445,'Revenue Data'!$D$6:$D$445,$A14,'Revenue Data'!$B$6:$B$445,DATE(2025,5,1)) -> 188207.94 | H14: =SUMIFS('Revenue Data'!$I$6:$I$445,'Revenue Data'!$D$6:$D$445,$A14,'Revenue Data'!$B$6:$B$445,DATE(2025,6,1)) -> 192385.11 | I14: =SUMIFS('Revenue Data'!$I$6:$I$445,'Revenue Data'!$D$6:$D$445,$A14,'Revenue Data'!$B$6:$B$445,DATE(2025,7,1)) -> 178939.86 | J14: =SUMIFS('Revenue Data'!$I$6:$I$445,'Revenue Data'!$D$6:$D$445,$A14,'Revenue Data'!$B$6:$B$445,DATE(2025,8,1)) -> 188439.35 | K14: =SUMIFS('Revenue Data'!$I$6:$I$445,'Revenue Data'!$D$6:$D$445,$A14,'Revenue Data'!$B$6:$B$445,DATE(2025,9,1)) -> 181724.85 | L14: =SUMIFS('Revenue Data'!$I$6:$I$445,'Revenue Data'!$D$6:$D$445,$A14,'Revenue Data'!$B$6:$B$445,DATE(2025,10,1)) -> 180326.51 | M14: =SUMIFS('Revenue Data'!$I$6:$I$445,'Revenue Data'!$D$6:$D$445,$A14,'Revenue Data'!$B$6:$B$445,DATE(2025,11,1)) -> 178081.59 | N14: =SUMIFS('Revenue Data'!$I$6:$I$445,'Revenue Data'!$D$6:$D$445,$A14,'Revenue Data'!$B$6:$B$445,DATE(2025,12,1)) -> 168455.8 | O14: =SUMIFS('Revenue Data'!$I$6:$I$445,'Revenue Data'!$D$6:$D$445,$A14,'Revenue Data'!$B$6:$B$445,DATE(2026,1,1)) -> 188474.41 | P14: =SUMIFS('Revenue Data'!$I$6:$I$445,'Revenue Data'!$D$6:$D$445,$A14,'Revenue Data'!$B$6:$B$445,DATE(2026,2,1)) -> 185269.65 | Q14: =SUMIFS('Revenue Data'!$I$6:$I$445,'Revenue Data'!$D$6:$D$445,$A14,'Revenue Data'!$B$6:$B$445,DATE(2026,3,1)) -> 193768.57 | R14: =SUMIFS('Revenue Data'!$I$6:$I$445,'Revenue Data'!$D$6:$D$445,$A14,'Revenue Data'!$B$6:$B$445,DATE(2026,4,1)) -> 171254.96 | S14: =SUMIFS('Revenue Data'!$I$6:$I$445,'Revenue Data'!$D$6:$D$445,$A14,'Revenue Data'!$B$6:$B$445,DATE(2026,5,1)) -> 194855.19 | T14: =SUMIFS('Revenue Data'!$I$6:$I$445,'Revenue Data'!$D$6:$D$445,$A14,'Revenue Data'!$B$6:$B$445,DATE(2026,6,1)) -> 208982 | U14: =SUMIFS('Revenue Data'!$I$6:$I$445,'Revenue Data'!$D$6:$D$445,$A14,'Revenue Data'!$B$6:$B$445,DATE(2026,7,1)) -> 193233.22 | V14: =SUMIFS('Revenue Data'!$I$6:$I$445,'Revenue Data'!$D$6:$D$445,$A14,'Revenue Data'!$B$6:$B$445,DATE(2026,8,1)) -> 187232.63 | W14: =SUMIFS('Revenue Data'!$I$6:$I$445,'Revenue Data'!$D$6:$D$445,$A14,'Revenue Data'!$B$6:$B$445,DATE(2026,9,1)) -> 191546.27 | X14: =SUM(C14:N14) -> 2170451.3 | Y14: =SUM(O14:W14) -> 1714616.9
A15: ACC-1010 | B15: Lamna Healthcare | C15: =SUMIFS('Revenue Data'!$I$6:$I$445,'Revenue Data'!$D$6:$D$445,$A15,'Revenue Data'!$B$6:$B$445,DATE(2025,1,1)) -> 85619.59 | D15: =SUMIFS('Revenue Data'!$I$6:$I$445,'Revenue Data'!$D$6:$D$445,$A15,'Revenue Data'!$B$6:$B$445,DATE(2025,2,1)) -> 87748.81 | E15: =SUMIFS('Revenue Data'!$I$6:$I$445,'Revenue Data'!$D$6:$D$445,$A15,'Revenue Data'!$B$6:$B$445,DATE(2025,3,1)) -> 96879.11 | F15: =SUMIFS('Revenue Data'!$I$6:$I$445,'Revenue Data'!$D$6:$D$445,$A15,'Revenue Data'!$B$6:$B$445,DATE(2025,4,1)) -> 92382.45 | G15: =SUMIFS('Revenue Data'!$I$6:$I$445,'Revenue Data'!$D$6:$D$445,$A15,'Revenue Data'!$B$6:$B$445,DATE(2025,5,1)) -> 90010.59 | H15: =SUMIFS('Revenue Data'!$I$6:$I$445,'Revenue Data'!$D$6:$D$445,$A15,'Revenue Data'!$B$6:$B$445,DATE(2025,6,1)) -> 96008.09 | I15: =SUMIFS('Revenue Data'!$I$6:$I$445,'Revenue Data'!$D$6:$D$445,$A15,'Revenue Data'!$B$6:$B$445,DATE(2025,7,1)) -> 82997.13 | J15: =SUMIFS('Revenue Data'!$I$6:$I$445,'Revenue Data'!$D$6:$D$445,$A15,'Revenue Data'!$B$6:$B$445,DATE(2025,8,1)) -> 92837.62 | K15: =SUMIFS('Revenue Data'!$I$6:$I$445,'Revenue Data'!$D$6:$D$445,$A15,'Revenue Data'!$B$6:$B$445,DATE(2025,9,1)) -> 91387 | L15: =SUMIFS('Revenue Data'!$I$6:$I$445,'Revenue Data'!$D$6:$D$445,$A15,'Revenue Data'!$B$6:$B$445,DATE(2025,10,1)) -> 92036.57 | M15: =SUMIFS('Revenue Data'!$I$6:$I$445,'Revenue Data'!$D$6:$D$445,$A15,'Revenue Data'!$B$6:$B$445,DATE(2025,11,1)) -> 93207.09 | N15: =SUMIFS('Revenue Data'!$I$6:$I$445,'Revenue Data'!$D$6:$D$445,$A15,'Revenue Data'!$B$6:$B$445,DATE(2025,12,1)) -> 83132.02 | O15: =SUMIFS('Revenue Data'!$I$6:$I$445,'Revenue Data'!$D$6:$D$445,$A15,'Revenue Data'!$B$6:$B$445,DATE(2026,1,1)) -> 89319.94 | P15: =SUMIFS('Revenue Data'!$I$6:$I$445,'Revenue Data'!$D$6:$D$445,$A15,'Revenue Data'!$B$6:$B$445,DATE(2026,2,1)) -> 91601.86 | Q15: =SUMIFS('Revenue Data'!$I$6:$I$445,'Revenue Data'!$D$6:$D$445,$A15,'Revenue Data'!$B$6:$B$445,DATE(2026,3,1)) -> 102373.05 | R15: =SUMIFS('Revenue Data'!$I$6:$I$445,'Revenue Data'!$D$6:$D$445,$A15,'Revenue Data'!$B$6:$B$445,DATE(2026,4,1)) -> 94529.33 | S15: =SUMIFS('Revenue Data'!$I$6:$I$445,'Revenue Data'!$D$6:$D$445,$A15,'Revenue Data'!$B$6:$B$445,DATE(2026,5,1)) -> 94884.35 | T15: =SUMIFS('Revenue Data'!$I$6:$I$445,'Revenue Data'!$D$6:$D$445,$A15,'Revenue Data'!$B$6:$B$445,DATE(2026,6,1)) -> 96113.46 | U15: =SUMIFS('Revenue Data'!$I$6:$I$445,'Revenue Data'!$D$6:$D$445,$A15,'Revenue Data'!$B$6:$B$445,DATE(2026,7,1)) -> 91070 | V15: =SUMIFS('Revenue Data'!$I$6:$I$445,'Revenue Data'!$D$6:$D$445,$A15,'Revenue Data'!$B$6:$B$445,DATE(2026,8,1)) -> 92941.1 | W15: =SUMIFS('Revenue Data'!$I$6:$I$445,'Revenue Data'!$D$6:$D$445,$A15,'Revenue Data'!$B$6:$B$445,DATE(2026,9,1)) -> 96904.98 | X15: =SUM(C15:N15) -> 1084246.1 | Y15: =SUM(O15:W15) -> 849738.07
A16: ACC-1011 | B16: Wide World Importers | C16: =SUMIFS('Revenue Data'!$I$6:$I$445,'Revenue Data'!$D$6:$D$445,$A16,'Revenue Data'!$B$6:$B$445,DATE(2025,1,1)) -> 88118.44 | D16: =SUMIFS('Revenue Data'!$I$6:$I$445,'Revenue Data'!$D$6:$D$445,$A16,'Revenue Data'!$B$6:$B$445,DATE(2025,2,1)) -> 87633.4 | E16: =SUMIFS('Revenue Data'!$I$6:$I$445,'Revenue Data'!$D$6:$D$445,$A16,'Revenue Data'!$B$6:$B$445,DATE(2025,3,1)) -> 88411.26 | F16: =SUMIFS('Revenue Data'!$I$6:$I$445,'Revenue Data'!$D$6:$D$445,$A16,'Revenue Data'!$B$6:$B$445,DATE(2025,4,1)) -> 86436.12 | G16: =SUMIFS('Revenue Data'!$I$6:$I$445,'Revenue Data'!$D$6:$D$445,$A16,'Revenue Data'!$B$6:$B$445,DATE(2025,5,1)) -> 88175.75 | H16: =SUMIFS('Revenue Data'!$I$6:$I$445,'Revenue Data'!$D$6:$D$445,$A16,'Revenue Data'!$B$6:$B$445,DATE(2025,6,1)) -> 88744.88 | I16: =SUMIFS('Revenue Data'!$I$6:$I$445,'Revenue Data'!$D$6:$D$445,$A16,'Revenue Data'!$B$6:$B$445,DATE(2025,7,1)) -> 84550.18 | J16: =SUMIFS('Revenue Data'!$I$6:$I$445,'Revenue Data'!$D$6:$D$445,$A16,'Revenue Data'!$B$6:$B$445,DATE(2025,8,1)) -> 89631.24 | K16: =SUMIFS('Revenue Data'!$I$6:$I$445,'Revenue Data'!$D$6:$D$445,$A16,'Revenue Data'!$B$6:$B$445,DATE(2025,9,1)) -> 91901.86 | L16: =SUMIFS('Revenue Data'!$I$6:$I$445,'Revenue Data'!$D$6:$D$445,$A16,'Revenue Data'!$B$6:$B$445,DATE(2025,10,1)) -> 86233.44 | M16: =SUMIFS('Revenue Data'!$I$6:$I$445,'Revenue Data'!$D$6:$D$445,$A16,'Revenue Data'!$B$6:$B$445,DATE(2025,11,1)) -> 87750.46 | N16: =SUMIFS('Revenue Data'!$I$6:$I$445,'Revenue Data'!$D$6:$D$445,$A16,'Revenue Data'!$B$6:$B$445,DATE(2025,12,1)) -> 80816.66 | O16: =SUMIFS('Revenue Data'!$I$6:$I$445,'Revenue Data'!$D$6:$D$445,$A16,'Revenue Data'!$B$6:$B$445,DATE(2026,1,1)) -> 78061.04 | P16: =SUMIFS('Revenue Data'!$I$6:$I$445,'Revenue Data'!$D$6:$D$445,$A16,'Revenue Data'!$B$6:$B$445,DATE(2026,2,1)) -> 75909.04 | Q16: =SUMIFS('Revenue Data'!$I$6:$I$445,'Revenue Data'!$D$6:$D$445,$A16,'Revenue Data'!$B$6:$B$445,DATE(2026,3,1)) -> 92098.67 | R16: =SUMIFS('Revenue Data'!$I$6:$I$445,'Revenue Data'!$D$6:$D$445,$A16,'Revenue Data'!$B$6:$B$445,DATE(2026,4,1)) -> 84886.18 | S16: =SUMIFS('Revenue Data'!$I$6:$I$445,'Revenue Data'!$D$6:$D$445,$A16,'Revenue Data'!$B$6:$B$445,DATE(2026,5,1)) -> 82497.79 | T16: =SUMIFS('Revenue Data'!$I$6:$I$445,'Revenue Data'!$D$6:$D$445,$A16,'Revenue Data'!$B$6:$B$445,DATE(2026,6,1)) -> 88250.08 | U16: =SUMIFS('Revenue Data'!$I$6:$I$445,'Revenue Data'!$D$6:$D$445,$A16,'Revenue Data'!$B$6:$B$445,DATE(2026,7,1)) -> 85433.78 | V16: =SUMIFS('Revenue Data'!$I$6:$I$445,'Revenue Data'!$D$6:$D$445,$A16,'Revenue Data'!$B$6:$B$445,DATE(2026,8,1)) -> 85496.88 | W16: =SUMIFS('Revenue Data'!$I$6:$I$445,'Revenue Data'!$D$6:$D$445,$A16,'Revenue Data'!$B$6:$B$445,DATE(2026,9,1)) -> 88142.18 | X16: =SUM(C16:N16) -> 1048403.7 | Y16: =SUM(O16:W16) -> 760775.64
A17: ACC-1012 | B17: Trey Research | C17: =SUMIFS('Revenue Data'!$I$6:$I$445,'Revenue Data'!$D$6:$D$445,$A17,'Revenue Data'!$B$6:$B$445,DATE(2025,1,1)) -> 27319 | D17: =SUMIFS('Revenue Data'!$I$6:$I$445,'Revenue Data'!$D$6:$D$445,$A17,'Revenue Data'!$B$6:$B$445,DATE(2025,2,1)) -> 28721.91 | E17: =SUMIFS('Revenue Data'!$I$6:$I$445,'Revenue Data'!$D$6:$D$445,$A17,'Revenue Data'!$B$6:$B$445,DATE(2025,3,1)) -> 30050.94 | F17: =SUMIFS('Revenue Data'!$I$6:$I$445,'Revenue Data'!$D$6:$D$445,$A17,'Revenue Data'!$B$6:$B$445,DATE(2025,4,1)) -> 28455.8 | G17: =SUMIFS('Revenue Data'!$I$6:$I$445,'Revenue Data'!$D$6:$D$445,$A17,'Revenue Data'!$B$6:$B$445,DATE(2025,5,1)) -> 30016.21 | H17: =SUMIFS('Revenue Data'!$I$6:$I$445,'Revenue Data'!$D$6:$D$445,$A17,'Revenue Data'!$B$6:$B$445,DATE(2025,6,1)) -> 31054.72 | I17: =SUMIFS('Revenue Data'!$I$6:$I$445,'Revenue Data'!$D$6:$D$445,$A17,'Revenue Data'!$B$6:$B$445,DATE(2025,7,1)) -> 28992.4 | J17: =SUMIFS('Revenue Data'!$I$6:$I$445,'Revenue Data'!$D$6:$D$445,$A17,'Revenue Data'!$B$6:$B$445,DATE(2025,8,1)) -> 28280.9 | K17: =SUMIFS('Revenue Data'!$I$6:$I$445,'Revenue Data'!$D$6:$D$445,$A17,'Revenue Data'!$B$6:$B$445,DATE(2025,9,1)) -> 30317.82 | L17: =SUMIFS('Revenue Data'!$I$6:$I$445,'Revenue Data'!$D$6:$D$445,$A17,'Revenue Data'!$B$6:$B$445,DATE(2025,10,1)) -> 32232.61 | M17: =SUMIFS('Revenue Data'!$I$6:$I$445,'Revenue Data'!$D$6:$D$445,$A17,'Revenue Data'!$B$6:$B$445,DATE(2025,11,1)) -> 29045.16 | N17: =SUMIFS('Revenue Data'!$I$6:$I$445,'Revenue Data'!$D$6:$D$445,$A17,'Revenue Data'!$B$6:$B$445,DATE(2025,12,1)) -> 25164.13 | O17: =SUMIFS('Revenue Data'!$I$6:$I$445,'Revenue Data'!$D$6:$D$445,$A17,'Revenue Data'!$B$6:$B$445,DATE(2026,1,1)) -> 38137.22 | P17: =SUMIFS('Revenue Data'!$I$6:$I$445,'Revenue Data'!$D$6:$D$445,$A17,'Revenue Data'!$B$6:$B$445,DATE(2026,2,1)) -> 42227.63 | Q17: =SUMIFS('Revenue Data'!$I$6:$I$445,'Revenue Data'!$D$6:$D$445,$A17,'Revenue Data'!$B$6:$B$445,DATE(2026,3,1)) -> 46120.45 | R17: =SUMIFS('Revenue Data'!$I$6:$I$445,'Revenue Data'!$D$6:$D$445,$A17,'Revenue Data'!$B$6:$B$445,DATE(2026,4,1)) -> 41616.77 | S17: =SUMIFS('Revenue Data'!$I$6:$I$445,'Revenue Data'!$D$6:$D$445,$A17,'Revenue Data'!$B$6:$B$445,DATE(2026,5,1)) -> 44782.03 | T17: =SUMIFS('Revenue Data'!$I$6:$I$445,'Revenue Data'!$D$6:$D$445,$A17,'Revenue Data'!$B$6:$B$445,DATE(2026,6,1)) -> 42343.73 | U17: =SUMIFS('Revenue Data'!$I$6:$I$445,'Revenue Data'!$D$6:$D$445,$A17,'Revenue Data'!$B$6:$B$445,DATE(2026,7,1)) -> 39982.38 | V17: =SUMIFS('Revenue Data'!$I$6:$I$445,'Revenue Data'!$D$6:$D$445,$A17,'Revenue Data'!$B$6:$B$445,DATE(2026,8,1)) -> 42017.11 | W17: =SUMIFS('Revenue Data'!$I$6:$I$445,'Revenue Data'!$D$6:$D$445,$A17,'Revenue Data'!$B$6:$B$445,DATE(2026,9,1)) -> 46303.84 | X17: =SUM(C17:N17) -> 349651.6 | Y17: =SUM(O17:W17) -> 383531.16
... A21: ACC-1018 | B21: Proseware Inc | C21: =SUMIFS('Revenue Data'!$I$6:$I$445,'Revenue Data'!$D$6:$D$445,$A21,'Revenue Data'!$B$6:$B$445,DATE(2025,1,1)) -> 0 | D21: =SUMIFS('Revenue Data'!$I$6:$I$445,'Revenue Data'!$D$6:$D$445,$A21,'Revenue Data'!$B$6:$B$445,DATE(2025,2,1)) -> 0 | E21: =SUMIFS('Revenue Data'!$I$6:$I$445,'Revenue Data'!$D$6:$D$445,$A21,'Revenue Data'!$B$6:$B$445,DATE(2025,3,1)) -> 0 | F21: =SUMIFS('Revenue Data'!$I$6:$I$445,'Revenue Data'!$D$6:$D$445,$A21,'Revenue Data'!$B$6:$B$445,DATE(2025,4,1)) -> 0 | G21: =SUMIFS('Revenue Data'!$I$6:$I$445,'Revenue Data'!$D$6:$D$445,$A21,'Revenue Data'!$B$6:$B$445,DATE(2025,5,1)) -> 0 | H21: =SUMIFS('Revenue Data'!$I$6:$I$445,'Revenue Data'!$D$6:$D$445,$A21,'Revenue Data'!$B$6:$B$445,DATE(2025,6,1)) -> 0 | I21: =SUMIFS('Revenue Data'!$I$6:$I$445,'Revenue Data'!$D$6:$D$445,$A21,'Revenue Data'!$B$6:$B$445,DATE(2025,7,1)) -> 0 | J21: =SUMIFS('Revenue Data'!$I$6:$I$445,'Revenue Data'!$D$6:$D$445,$A21,'Revenue Data'!$B$6:$B$445,DATE(2025,8,1)) -> 0 | K21: =SUMIFS('Revenue Data'!$I$6:$I$445,'Revenue Data'!$D$6:$D$445,$A21,'Revenue Data'!$B$6:$B$445,DATE(2025,9,1)) -> 0 | L21: =SUMIFS('Revenue Data'!$I$6:$I$445,'Revenue Data'!$D$6:$D$445,$A21,'Revenue Data'!$B$6:$B$445,DATE(2025,10,1)) -> 0 | M21: =SUMIFS('Revenue Data'!$I$6:$I$445,'Revenue Data'!$D$6:$D$445,$A21,'Revenue Data'!$B$6:$B$445,DATE(2025,11,1)) -> 0 | N21: =SUMIFS('Revenue Data'!$I$6:$I$445,'Revenue Data'!$D$6:$D$445,$A21,'Revenue Data'!$B$6:$B$445,DATE(2025,12,1)) -> 0 | O21: =SUMIFS('Revenue Data'!$I$6:$I$445,'Revenue Data'!$D$6:$D$445,$A21,'Revenue Data'!$B$6:$B$445,DATE(2026,1,1)) -> 0 | P21: =SUMIFS('Revenue Data'!$I$6:$I$445,'Revenue Data'!$D$6:$D$445,$A21,'Revenue Data'!$B$6:$B$445,DATE(2026,2,1)) -> 0 | Q21: =SUMIFS('Revenue Data'!$I$6:$I$445,'Revenue Data'!$D$6:$D$445,$A21,'Revenue Data'!$B$6:$B$445,DATE(2026,3,1)) -> 0 | R21: =SUMIFS('Revenue Data'!$I$6:$I$445,'Revenue Data'!$D$6:$D$445,$A21,'Revenue Data'!$B$6:$B$445,DATE(2026,4,1)) -> 0 | S21: =SUMIFS('Revenue Data'!$I$6:$I$445,'Revenue Data'!$D$6:$D$445,$A21,'Revenue Data'!$B$6:$B$445,DATE(2026,5,1)) -> 0 | T21: =SUMIFS('Revenue Data'!$I$6:$I$445,'Revenue Data'!$D$6:$D$445,$A21,'Revenue Data'!$B$6:$B$445,DATE(2026,6,1)) -> 0 | U21: =SUMIFS('Revenue Data'!$I$6:$I$445,'Revenue Data'!$D$6:$D$445,$A21,'Revenue Data'!$B$6:$B$445,DATE(2026,7,1)) -> 0 | V21: =SUMIFS('Revenue Data'!$I$6:$I$445,'Revenue Data'!$D$6:$D$445,$A21,'Revenue Data'!$B$6:$B$445,DATE(2026,8,1)) -> 0 | W21: =SUMIFS('Revenue Data'!$I$6:$I$445,'Revenue Data'!$D$6:$D$445,$A21,'Revenue Data'!$B$6:$B$445,DATE(2026,9,1)) -> 49024.02 | X21: =SUM(C21:N21) -> 0 | Y21: =SUM(O21:W21) -> 49024.02
B22: Total | C22: =SUM(C6:C21) -> 981516.84 | D22: =SUM(D6:D21) -> 1009677.5 | E22: =SUM(E6:E21) -> 1273399.3 | F22: =SUM(F6:F21) -> 1241155.9 | G22: =SUM(G6:G21) -> 1260850.6 | H22: =SUM(H6:H21) -> 1382635.9 | I22: =SUM(I6:I21) -> 1308532.1 | J22: =SUM(J6:J21) -> 1333061.6 | ... Y22: =SUM(Y6:Y21) -> 14631637

Sheet By Service Line (Monthly)
A1: Revenue by service line by month (USD)
A2: SUMIFS over Revenue Data
A3: Classification: Confidential
A5: Service line | B5: Jan-25 | C5: Feb-25 | D5: Mar-25 | E5: Apr-25 | F5: May-25 | G5: Jun-25 | H5: Jul-25 | I5: Aug-25 | J5: Sep-25 | K5: Oct-25 | L5: Nov-25 | M5: Dec-25 | N5: Jan-26 | O5: Feb-26 | P5: Mar-26 | Q5: Apr-26 | R5: May-26 | S5: Jun-26 | T5: Jul-26 | U5: Aug-26 | V5: Sep-26
A6: Cloud & Infrastructure | B6: =SUMIFS('Revenue Data'!$I$6:$I$445,'Revenue Data'!$H$6:$H$445,$A6,'Revenue Data'!$B$6:$B$445,DATE(2025,1,1)) -> 209217.59 | C6: =SUMIFS('Revenue Data'!$I$6:$I$445,'Revenue Data'!$H$6:$H$445,$A6,'Revenue Data'!$B$6:$B$445,DATE(2025,2,1)) -> 218419.57 | D6: =SUMIFS('Revenue Data'!$I$6:$I$445,'Revenue Data'!$H$6:$H$445,$A6,'Revenue Data'!$B$6:$B$445,DATE(2025,3,1)) -> 233330.21 | E6: =SUMIFS('Revenue Data'!$I$6:$I$445,'Revenue Data'!$H$6:$H$445,$A6,'Revenue Data'!$B$6:$B$445,DATE(2025,4,1)) -> 218640.91 | F6: =SUMIFS('Revenue Data'!$I$6:$I$445,'Revenue Data'!$H$6:$H$445,$A6,'Revenue Data'!$B$6:$B$445,DATE(2025,5,1)) -> 222937.63 | G6: =SUMIFS('Revenue Data'!$I$6:$I$445,'Revenue Data'!$H$6:$H$445,$A6,'Revenue Data'!$B$6:$B$445,DATE(2025,6,1)) -> 222010.57 | H6: =SUMIFS('Revenue Data'!$I$6:$I$445,'Revenue Data'!$H$6:$H$445,$A6,'Revenue Data'!$B$6:$B$445,DATE(2025,7,1)) -> 216942.26 | I6: =SUMIFS('Revenue Data'!$I$6:$I$445,'Revenue Data'!$H$6:$H$445,$A6,'Revenue Data'!$B$6:$B$445,DATE(2025,8,1)) -> 225039.73 | J6: =SUMIFS('Revenue Data'!$I$6:$I$445,'Revenue Data'!$H$6:$H$445,$A6,'Revenue Data'!$B$6:$B$445,DATE(2025,9,1)) -> 229183.58 | K6: =SUMIFS('Revenue Data'!$I$6:$I$445,'Revenue Data'!$H$6:$H$445,$A6,'Revenue Data'!$B$6:$B$445,DATE(2025,10,1)) -> 220045.74 | L6: =SUMIFS('Revenue Data'!$I$6:$I$445,'Revenue Data'!$H$6:$H$445,$A6,'Revenue Data'!$B$6:$B$445,DATE(2025,11,1)) -> 224149.28 | M6: =SUMIFS('Revenue Data'!$I$6:$I$445,'Revenue Data'!$H$6:$H$445,$A6,'Revenue Data'!$B$6:$B$445,DATE(2025,12,1)) -> 199328.57 | N6: =SUMIFS('Revenue Data'!$I$6:$I$445,'Revenue Data'!$H$6:$H$445,$A6,'Revenue Data'!$B$6:$B$445,DATE(2026,1,1)) -> 211589.29 | O6: =SUMIFS('Revenue Data'!$I$6:$I$445,'Revenue Data'!$H$6:$H$445,$A6,'Revenue Data'!$B$6:$B$445,DATE(2026,2,1)) -> 221397.23 | P6: =SUMIFS('Revenue Data'!$I$6:$I$445,'Revenue Data'!$H$6:$H$445,$A6,'Revenue Data'!$B$6:$B$445,DATE(2026,3,1)) -> 236214.54 | Q6: =SUMIFS('Revenue Data'!$I$6:$I$445,'Revenue Data'!$H$6:$H$445,$A6,'Revenue Data'!$B$6:$B$445,DATE(2026,4,1)) -> 225709.6 | R6: =SUMIFS('Revenue Data'!$I$6:$I$445,'Revenue Data'!$H$6:$H$445,$A6,'Revenue Data'!$B$6:$B$445,DATE(2026,5,1)) -> 268849.49 | S6: =SUMIFS('Revenue Data'!$I$6:$I$445,'Revenue Data'!$H$6:$H$445,$A6,'Revenue Data'!$B$6:$B$445,DATE(2026,6,1)) -> 274477.94 | T6: =SUMIFS('Revenue Data'!$I$6:$I$445,'Revenue Data'!$H$6:$H$445,$A6,'Revenue Data'!$B$6:$B$445,DATE(2026,7,1)) -> 228277.51 | U6: =SUMIFS('Revenue Data'!$I$6:$I$445,'Revenue Data'!$H$6:$H$445,$A6,'Revenue Data'!$B$6:$B$445,DATE(2026,8,1)) -> 236253.76 | V6: =SUMIFS('Revenue Data'!$I$6:$I$445,'Revenue Data'!$H$6:$H$445,$A6,'Revenue Data'!$B$6:$B$445,DATE(2026,9,1)) -> 256638.28
A7: Data & AI | B7: =SUMIFS('Revenue Data'!$I$6:$I$445,'Revenue Data'!$H$6:$H$445,$A7,'Revenue Data'!$B$6:$B$445,DATE(2025,1,1)) -> 50763.39 | C7: =SUMIFS('Revenue Data'!$I$6:$I$445,'Revenue Data'!$H$6:$H$445,$A7,'Revenue Data'!$B$6:$B$445,DATE(2025,2,1)) -> 51968.68 | D7: =SUMIFS('Revenue Data'!$I$6:$I$445,'Revenue Data'!$H$6:$H$445,$A7,'Revenue Data'!$B$6:$B$445,DATE(2025,3,1)) -> 57449.36 | E7: =SUMIFS('Revenue Data'!$I$6:$I$445,'Revenue Data'!$H$6:$H$445,$A7,'Revenue Data'!$B$6:$B$445,DATE(2025,4,1)) -> 101080.44 | F7: =SUMIFS('Revenue Data'!$I$6:$I$445,'Revenue Data'!$H$6:$H$445,$A7,'Revenue Data'!$B$6:$B$445,DATE(2025,5,1)) -> 103197.89 | G7: =SUMIFS('Revenue Data'!$I$6:$I$445,'Revenue Data'!$H$6:$H$445,$A7,'Revenue Data'!$B$6:$B$445,DATE(2025,6,1)) -> 189771.86 | H7: =SUMIFS('Revenue Data'!$I$6:$I$445,'Revenue Data'!$H$6:$H$445,$A7,'Revenue Data'!$B$6:$B$445,DATE(2025,7,1)) -> 172245.37 | I7: =SUMIFS('Revenue Data'!$I$6:$I$445,'Revenue Data'!$H$6:$H$445,$A7,'Revenue Data'!$B$6:$B$445,DATE(2025,8,1)) -> 170166.21 | J7: =SUMIFS('Revenue Data'!$I$6:$I$445,'Revenue Data'!$H$6:$H$445,$A7,'Revenue Data'!$B$6:$B$445,DATE(2025,9,1)) -> 266593.1 | K7: =SUMIFS('Revenue Data'!$I$6:$I$445,'Revenue Data'!$H$6:$H$445,$A7,'Revenue Data'!$B$6:$B$445,DATE(2025,10,1)) -> 256349.42 | L7: =SUMIFS('Revenue Data'!$I$6:$I$445,'Revenue Data'!$H$6:$H$445,$A7,'Revenue Data'!$B$6:$B$445,DATE(2025,11,1)) -> 250155.24 | M7: =SUMIFS('Revenue Data'!$I$6:$I$445,'Revenue Data'!$H$6:$H$445,$A7,'Revenue Data'!$B$6:$B$445,DATE(2025,12,1)) -> 229177.93 | N7: =SUMIFS('Revenue Data'!$I$6:$I$445,'Revenue Data'!$H$6:$H$445,$A7,'Revenue Data'!$B$6:$B$445,DATE(2026,1,1)) -> 343520.75 | O7: =SUMIFS('Revenue Data'!$I$6:$I$445,'Revenue Data'!$H$6:$H$445,$A7,'Revenue Data'!$B$6:$B$445,DATE(2026,2,1)) -> 361972.7 | P7: =SUMIFS('Revenue Data'!$I$6:$I$445,'Revenue Data'!$H$6:$H$445,$A7,'Revenue Data'!$B$6:$B$445,DATE(2026,3,1)) -> 382631.12 | Q7: =SUMIFS('Revenue Data'!$I$6:$I$445,'Revenue Data'!$H$6:$H$445,$A7,'Revenue Data'!$B$6:$B$445,DATE(2026,4,1)) -> 354212.37 | R7: =SUMIFS('Revenue Data'!$I$6:$I$445,'Revenue Data'!$H$6:$H$445,$A7,'Revenue Data'!$B$6:$B$445,DATE(2026,5,1)) -> 377081.52 | S7: =SUMIFS('Revenue Data'!$I$6:$I$445,'Revenue Data'!$H$6:$H$445,$A7,'Revenue Data'!$B$6:$B$445,DATE(2026,6,1)) -> 386440.58 | T7: =SUMIFS('Revenue Data'!$I$6:$I$445,'Revenue Data'!$H$6:$H$445,$A7,'Revenue Data'!$B$6:$B$445,DATE(2026,7,1)) -> 360174.29 | U7: =SUMIFS('Revenue Data'!$I$6:$I$445,'Revenue Data'!$H$6:$H$445,$A7,'Revenue Data'!$B$6:$B$445,DATE(2026,8,1)) -> 434559.19 | V7: =SUMIFS('Revenue Data'!$I$6:$I$445,'Revenue Data'!$H$6:$H$445,$A7,'Revenue Data'!$B$6:$B$445,DATE(2026,9,1)) -> 445413.06
A8: Application Modernization | B8: =SUMIFS('Revenue Data'!$I$6:$I$445,'Revenue Data'!$H$6:$H$445,$A8,'Revenue Data'!$B$6:$B$445,DATE(2025,1,1)) -> 68946.27 | C8: =SUMIFS('Revenue Data'!$I$6:$I$445,'Revenue Data'!$H$6:$H$445,$A8,'Revenue Data'!$B$6:$B$445,DATE(2025,2,1)) -> 71181.89 | D8: =SUMIFS('Revenue Data'!$I$6:$I$445,'Revenue Data'!$H$6:$H$445,$A8,'Revenue Data'!$B$6:$B$445,DATE(2025,3,1)) -> 269372.53 | E8: =SUMIFS('Revenue Data'!$I$6:$I$445,'Revenue Data'!$H$6:$H$445,$A8,'Revenue Data'!$B$6:$B$445,DATE(2025,4,1)) -> 247287.81 | F8: =SUMIFS('Revenue Data'!$I$6:$I$445,'Revenue Data'!$H$6:$H$445,$A8,'Revenue Data'!$B$6:$B$445,DATE(2025,5,1)) -> 241992.2 | G8: =SUMIFS('Revenue Data'!$I$6:$I$445,'Revenue Data'!$H$6:$H$445,$A8,'Revenue Data'!$B$6:$B$445,DATE(2025,6,1)) -> 255820.24 | H8: =SUMIFS('Revenue Data'!$I$6:$I$445,'Revenue Data'!$H$6:$H$445,$A8,'Revenue Data'!$B$6:$B$445,DATE(2025,7,1)) -> 254996.58 | I8: =SUMIFS('Revenue Data'!$I$6:$I$445,'Revenue Data'!$H$6:$H$445,$A8,'Revenue Data'!$B$6:$B$445,DATE(2025,8,1)) -> 244804.38 | J8: =SUMIFS('Revenue Data'!$I$6:$I$445,'Revenue Data'!$H$6:$H$445,$A8,'Revenue Data'!$B$6:$B$445,DATE(2025,9,1)) -> 266829.77 | K8: =SUMIFS('Revenue Data'!$I$6:$I$445,'Revenue Data'!$H$6:$H$445,$A8,'Revenue Data'!$B$6:$B$445,DATE(2025,10,1)) -> 241165.07 | L8: =SUMIFS('Revenue Data'!$I$6:$I$445,'Revenue Data'!$H$6:$H$445,$A8,'Revenue Data'!$B$6:$B$445,DATE(2025,11,1)) -> 260243.35 | M8: =SUMIFS('Revenue Data'!$I$6:$I$445,'Revenue Data'!$H$6:$H$445,$A8,'Revenue Data'!$B$6:$B$445,DATE(2025,12,1)) -> 227450.28 | N8: =SUMIFS('Revenue Data'!$I$6:$I$445,'Revenue Data'!$H$6:$H$445,$A8,'Revenue Data'!$B$6:$B$445,DATE(2026,1,1)) -> 237697.44 | O8: =SUMIFS('Revenue Data'!$I$6:$I$445,'Revenue Data'!$H$6:$H$445,$A8,'Revenue Data'!$B$6:$B$445,DATE(2026,2,1)) -> 253408.74 | P8: =SUMIFS('Revenue Data'!$I$6:$I$445,'Revenue Data'!$H$6:$H$445,$A8,'Revenue Data'!$B$6:$B$445,DATE(2026,3,1)) -> 277372.18 | Q8: =SUMIFS('Revenue Data'!$I$6:$I$445,'Revenue Data'!$H$6:$H$445,$A8,'Revenue Data'!$B$6:$B$445,DATE(2026,4,1)) -> 250932.1 | R8: =SUMIFS('Revenue Data'!$I$6:$I$445,'Revenue Data'!$H$6:$H$445,$A8,'Revenue Data'!$B$6:$B$445,DATE(2026,5,1)) -> 267847.29 | S8: =SUMIFS('Revenue Data'!$I$6:$I$445,'Revenue Data'!$H$6:$H$445,$A8,'Revenue Data'!$B$6:$B$445,DATE(2026,6,1)) -> 269040.3 | T8: =SUMIFS('Revenue Data'!$I$6:$I$445,'Revenue Data'!$H$6:$H$445,$A8,'Revenue Data'!$B$6:$B$445,DATE(2026,7,1)) -> 260793.54 | U8: =SUMIFS('Revenue Data'!$I$6:$I$445,'Revenue Data'!$H$6:$H$445,$A8,'Revenue Data'!$B$6:$B$445,DATE(2026,8,1)) -> 247491.55 | V8: =SUMIFS('Revenue Data'!$I$6:$I$445,'Revenue Data'!$H$6:$H$445,$A8,'Revenue Data'!$B$6:$B$445,DATE(2026,9,1)) -> 313862.17
A9: Digital Commerce | B9: =SUMIFS('Revenue Data'!$I$6:$I$445,'Revenue Data'!$H$6:$H$445,$A9,'Revenue Data'!$B$6:$B$445,DATE(2025,1,1)) -> 45089.13 | C9: =SUMIFS('Revenue Data'!$I$6:$I$445,'Revenue Data'!$H$6:$H$445,$A9,'Revenue Data'!$B$6:$B$445,DATE(2025,2,1)) -> 51234.47 | D9: =SUMIFS('Revenue Data'!$I$6:$I$445,'Revenue Data'!$H$6:$H$445,$A9,'Revenue Data'!$B$6:$B$445,DATE(2025,3,1)) -> 52680.63 | E9: =SUMIFS('Revenue Data'!$I$6:$I$445,'Revenue Data'!$H$6:$H$445,$A9,'Revenue Data'!$B$6:$B$445,DATE(2025,4,1)) -> 46667.92 | F9: =SUMIFS('Revenue Data'!$I$6:$I$445,'Revenue Data'!$H$6:$H$445,$A9,'Revenue Data'!$B$6:$B$445,DATE(2025,5,1)) -> 47897.9 | G9: =SUMIFS('Revenue Data'!$I$6:$I$445,'Revenue Data'!$H$6:$H$445,$A9,'Revenue Data'!$B$6:$B$445,DATE(2025,6,1)) -> 51584.91 | H9: =SUMIFS('Revenue Data'!$I$6:$I$445,'Revenue Data'!$H$6:$H$445,$A9,'Revenue Data'!$B$6:$B$445,DATE(2025,7,1)) -> 46887.9 | I9: =SUMIFS('Revenue Data'!$I$6:$I$445,'Revenue Data'!$H$6:$H$445,$A9,'Revenue Data'!$B$6:$B$445,DATE(2025,8,1)) -> 51136.6 | J9: =SUMIFS('Revenue Data'!$I$6:$I$445,'Revenue Data'!$H$6:$H$445,$A9,'Revenue Data'!$B$6:$B$445,DATE(2025,9,1)) -> 50971.59 | K9: =SUMIFS('Revenue Data'!$I$6:$I$445,'Revenue Data'!$H$6:$H$445,$A9,'Revenue Data'!$B$6:$B$445,DATE(2025,10,1)) -> 50945.89 | L9: =SUMIFS('Revenue Data'!$I$6:$I$445,'Revenue Data'!$H$6:$H$445,$A9,'Revenue Data'!$B$6:$B$445,DATE(2025,11,1)) -> 48695.52 | M9: =SUMIFS('Revenue Data'!$I$6:$I$445,'Revenue Data'!$H$6:$H$445,$A9,'Revenue Data'!$B$6:$B$445,DATE(2025,12,1)) -> 47654.19 | N9: =SUMIFS('Revenue Data'!$I$6:$I$445,'Revenue Data'!$H$6:$H$445,$A9,'Revenue Data'!$B$6:$B$445,DATE(2026,1,1)) -> 53610.17 | O9: =SUMIFS('Revenue Data'!$I$6:$I$445,'Revenue Data'!$H$6:$H$445,$A9,'Revenue Data'!$B$6:$B$445,DATE(2026,2,1)) -> 56447.35 | P9: =SUMIFS('Revenue Data'!$I$6:$I$445,'Revenue Data'!$H$6:$H$445,$A9,'Revenue Data'!$B$6:$B$445,DATE(2026,3,1)) -> 56941.25 | Q9: =SUMIFS('Revenue Data'!$I$6:$I$445,'Revenue Data'!$H$6:$H$445,$A9,'Revenue Data'!$B$6:$B$445,DATE(2026,4,1)) -> 58974.98 | R9: =SUMIFS('Revenue Data'!$I$6:$I$445,'Revenue Data'!$H$6:$H$445,$A9,'Revenue Data'!$B$6:$B$445,DATE(2026,5,1)) -> 59640.23 | S9: =SUMIFS('Revenue Data'!$I$6:$I$445,'Revenue Data'!$H$6:$H$445,$A9,'Revenue Data'!$B$6:$B$445,DATE(2026,6,1)) -> 61298.96 | T9: =SUMIFS('Revenue Data'!$I$6:$I$445,'Revenue Data'!$H$6:$H$445,$A9,'Revenue Data'!$B$6:$B$445,DATE(2026,7,1)) -> 90331.52 | U9: =SUMIFS('Revenue Data'!$I$6:$I$445,'Revenue Data'!$H$6:$H$445,$A9,'Revenue Data'!$B$6:$B$445,DATE(2026,8,1)) -> 94178.17 | V9: =SUMIFS('Revenue Data'!$I$6:$I$445,'Revenue Data'!$H$6:$H$445,$A9,'Revenue Data'!$B$6:$B$445,DATE(2026,9,1)) -> 96246.99
A10: Managed Services | B10: =SUMIFS('Revenue Data'!$I$6:$I$445,'Revenue Data'!$H$6:$H$445,$A10,'Revenue Data'!$B$6:$B$445,DATE(2025,1,1)) -> 565147.16 | C10: =SUMIFS('Revenue Data'!$I$6:$I$445,'Revenue Data'!$H$6:$H$445,$A10,'Revenue Data'!$B$6:$B$445,DATE(2025,2,1)) -> 570941.41 | D10: =SUMIFS('Revenue Data'!$I$6:$I$445,'Revenue Data'!$H$6:$H$445,$A10,'Revenue Data'!$B$6:$B$445,DATE(2025,3,1)) -> 612096.27 | E10: =SUMIFS('Revenue Data'!$I$6:$I$445,'Revenue Data'!$H$6:$H$445,$A10,'Revenue Data'!$B$6:$B$445,DATE(2025,4,1)) -> 583262.83 | F10: =SUMIFS('Revenue Data'!$I$6:$I$445,'Revenue Data'!$H$6:$H$445,$A10,'Revenue Data'!$B$6:$B$445,DATE(2025,5,1)) -> 599401.95 | G10: =SUMIFS('Revenue Data'!$I$6:$I$445,'Revenue Data'!$H$6:$H$445,$A10,'Revenue Data'!$B$6:$B$445,DATE(2025,6,1)) -> 615791.96 | H10: =SUMIFS('Revenue Data'!$I$6:$I$445,'Revenue Data'!$H$6:$H$445,$A10,'Revenue Data'!$B$6:$B$445,DATE(2025,7,1)) -> 574346.57 | I10: =SUMIFS('Revenue Data'!$I$6:$I$445,'Revenue Data'!$H$6:$H$445,$A10,'Revenue Data'!$B$6:$B$445,DATE(2025,8,1)) -> 596154.28 | J10: =SUMIFS('Revenue Data'!$I$6:$I$445,'Revenue Data'!$H$6:$H$445,$A10,'Revenue Data'!$B$6:$B$445,DATE(2025,9,1)) -> 611071.14 | K10: =SUMIFS('Revenue Data'!$I$6:$I$445,'Revenue Data'!$H$6:$H$445,$A10,'Revenue Data'!$B$6:$B$445,DATE(2025,10,1)) -> 585473.36 | L10: =SUMIFS('Revenue Data'!$I$6:$I$445,'Revenue Data'!$H$6:$H$445,$A10,'Revenue Data'!$B$6:$B$445,DATE(2025,11,1)) -> 575857.17 | M10: =SUMIFS('Revenue Data'!$I$6:$I$445,'Revenue Data'!$H$6:$H$445,$A10,'Revenue Data'!$B$6:$B$445,DATE(2025,12,1)) -> 553031.76 | N10: =SUMIFS('Revenue Data'!$I$6:$I$445,'Revenue Data'!$H$6:$H$445,$A10,'Revenue Data'!$B$6:$B$445,DATE(2026,1,1)) -> 597127.46 | O10: =SUMIFS('Revenue Data'!$I$6:$I$445,'Revenue Data'!$H$6:$H$445,$A10,'Revenue Data'!$B$6:$B$445,DATE(2026,2,1)) -> 590670.33 | P10: =SUMIFS('Revenue Data'!$I$6:$I$445,'Revenue Data'!$H$6:$H$445,$A10,'Revenue Data'!$B$6:$B$445,DATE(2026,3,1)) -> 645121.21 | Q10: =SUMIFS('Revenue Data'!$I$6:$I$445,'Revenue Data'!$H$6:$H$445,$A10,'Revenue Data'!$B$6:$B$445,DATE(2026,4,1)) -> 594513.63 | R10: =SUMIFS('Revenue Data'!$I$6:$I$445,'Revenue Data'!$H$6:$H$445,$A10,'Revenue Data'!$B$6:$B$445,DATE(2026,5,1)) -> 611902.49 | S10: =SUMIFS('Revenue Data'!$I$6:$I$445,'Revenue Data'!$H$6:$H$445,$A10,'Revenue Data'!$B$6:$B$445,DATE(2026,6,1)) -> 638439.48 | T10: =SUMIFS('Revenue Data'!$I$6:$I$445,'Revenue Data'!$H$6:$H$445,$A10,'Revenue Data'!$B$6:$B$445,DATE(2026,7,1)) -> 605474 | U10: =SUMIFS('Revenue Data'!$I$6:$I$445,'Revenue Data'!$H$6:$H$445,$A10,'Revenue Data'!$B$6:$B$445,DATE(2026,8,1)) -> 604689.96 | V10: =SUMIFS('Revenue Data'!$I$6:$I$445,'Revenue Data'!$H$6:$H$445,$A10,'Revenue Data'!$B$6:$B$445,DATE(2026,9,1)) -> 641211.81
A11: Cybersecurity | B11: =SUMIFS('Revenue Data'!$I$6:$I$445,'Revenue Data'!$H$6:$H$445,$A11,'Revenue Data'!$B$6:$B$445,DATE(2025,1,1)) -> 19805.74 | C11: =SUMIFS('Revenue Data'!$I$6:$I$445,'Revenue Data'!$H$6:$H$445,$A11,'Revenue Data'!$B$6:$B$445,DATE(2025,2,1)) -> 21561.82 | D11: =SUMIFS('Revenue Data'!$I$6:$I$445,'Revenue Data'!$H$6:$H$445,$A11,'Revenue Data'!$B$6:$B$445,DATE(2025,3,1)) -> 21548.47 | E11: =SUMIFS('Revenue Data'!$I$6:$I$445,'Revenue Data'!$H$6:$H$445,$A11,'Revenue Data'!$B$6:$B$445,DATE(2025,4,1)) -> 20089.61 | F11: =SUMIFS('Revenue Data'!$I$6:$I$445,'Revenue Data'!$H$6:$H$445,$A11,'Revenue Data'!$B$6:$B$445,DATE(2025,5,1)) -> 20473.95 | G11: =SUMIFS('Revenue Data'!$I$6:$I$445,'Revenue Data'!$H$6:$H$445,$A11,'Revenue Data'!$B$6:$B$445,DATE(2025,6,1)) -> 21971.64 | H11: =SUMIFS('Revenue Data'!$I$6:$I$445,'Revenue Data'!$H$6:$H$445,$A11,'Revenue Data'!$B$6:$B$445,DATE(2025,7,1)) -> 20712.62 | I11: =SUMIFS('Revenue Data'!$I$6:$I$445,'Revenue Data'!$H$6:$H$445,$A11,'Revenue Data'!$B$6:$B$445,DATE(2025,8,1)) -> 20406.99 | J11: =SUMIFS('Revenue Data'!$I$6:$I$445,'Revenue Data'!$H$6:$H$445,$A11,'Revenue Data'!$B$6:$B$445,DATE(2025,9,1)) -> 21176.3 | K11: =SUMIFS('Revenue Data'!$I$6:$I$445,'Revenue Data'!$H$6:$H$445,$A11,'Revenue Data'!$B$6:$B$445,DATE(2025,10,1)) -> 21599.73 | L11: =SUMIFS('Revenue Data'!$I$6:$I$445,'Revenue Data'!$H$6:$H$445,$A11,'Revenue Data'!$B$6:$B$445,DATE(2025,11,1)) -> 21266.23 | M11: =SUMIFS('Revenue Data'!$I$6:$I$445,'Revenue Data'!$H$6:$H$445,$A11,'Revenue Data'!$B$6:$B$445,DATE(2025,12,1)) -> 19452.55 | N11: =SUMIFS('Revenue Data'!$I$6:$I$445,'Revenue Data'!$H$6:$H$445,$A11,'Revenue Data'!$B$6:$B$445,DATE(2026,1,1)) -> 18653.94 | O11: =SUMIFS('Revenue Data'!$I$6:$I$445,'Revenue Data'!$H$6:$H$445,$A11,'Revenue Data'!$B$6:$B$445,DATE(2026,2,1)) -> 18012.55 | P11: =SUMIFS('Revenue Data'!$I$6:$I$445,'Revenue Data'!$H$6:$H$445,$A11,'Revenue Data'!$B$6:$B$445,DATE(2026,3,1)) -> 19230.16 | Q11: =SUMIFS('Revenue Data'!$I$6:$I$445,'Revenue Data'!$H$6:$H$445,$A11,'Revenue Data'!$B$6:$B$445,DATE(2026,4,1)) -> 18188.33 | R11: =SUMIFS('Revenue Data'!$I$6:$I$445,'Revenue Data'!$H$6:$H$445,$A11,'Revenue Data'!$B$6:$B$445,DATE(2026,5,1)) -> 34398.28 | S11: =SUMIFS('Revenue Data'!$I$6:$I$445,'Revenue Data'!$H$6:$H$445,$A11,'Revenue Data'!$B$6:$B$445,DATE(2026,6,1)) -> 36143.49 | T11: =SUMIFS('Revenue Data'!$I$6:$I$445,'Revenue Data'!$H$6:$H$445,$A11,'Revenue Data'!$B$6:$B$445,DATE(2026,7,1)) -> 33509.17 | U11: =SUMIFS('Revenue Data'!$I$6:$I$445,'Revenue Data'!$H$6:$H$445,$A11,'Revenue Data'!$B$6:$B$445,DATE(2026,8,1)) -> 34294.76 | V11: =SUMIFS('Revenue Data'!$I$6:$I$445,'Revenue Data'!$H$6:$H$445,$A11,'Revenue Data'!$B$6:$B$445,DATE(2026,9,1)) -> 20566.11
A12: Intelligent Automation | B12: =SUMIFS('Revenue Data'!$I$6:$I$445,'Revenue Data'!$H$6:$H$445,$A12,'Revenue Data'!$B$6:$B$445,DATE(2025,1,1)) -> 22547.56 | C12: =SUMIFS('Revenue Data'!$I$6:$I$445,'Revenue Data'!$H$6:$H$445,$A12,'Revenue Data'!$B$6:$B$445,DATE(2025,2,1)) -> 24369.69 | D12: =SUMIFS('Revenue Data'!$I$6:$I$445,'Revenue Data'!$H$6:$H$445,$A12,'Revenue Data'!$B$6:$B$445,DATE(2025,3,1)) -> 26921.81 | E12: =SUMIFS('Revenue Data'!$I$6:$I$445,'Revenue Data'!$H$6:$H$445,$A12,'Revenue Data'!$B$6:$B$445,DATE(2025,4,1)) -> 24126.41 | F12: =SUMIFS('Revenue Data'!$I$6:$I$445,'Revenue Data'!$H$6:$H$445,$A12,'Revenue Data'!$B$6:$B$445,DATE(2025,5,1)) -> 24949.03 | G12: =SUMIFS('Revenue Data'!$I$6:$I$445,'Revenue Data'!$H$6:$H$445,$A12,'Revenue Data'!$B$6:$B$445,DATE(2025,6,1)) -> 25684.68 | H12: =SUMIFS('Revenue Data'!$I$6:$I$445,'Revenue Data'!$H$6:$H$445,$A12,'Revenue Data'!$B$6:$B$445,DATE(2025,7,1)) -> 22400.81 | I12: =SUMIFS('Revenue Data'!$I$6:$I$445,'Revenue Data'!$H$6:$H$445,$A12,'Revenue Data'!$B$6:$B$445,DATE(2025,8,1)) -> 25353.44 | J12: =SUMIFS('Revenue Data'!$I$6:$I$445,'Revenue Data'!$H$6:$H$445,$A12,'Revenue Data'!$B$6:$B$445,DATE(2025,9,1)) -> 25416.13 | K12: =SUMIFS('Revenue Data'!$I$6:$I$445,'Revenue Data'!$H$6:$H$445,$A12,'Revenue Data'!$B$6:$B$445,DATE(2025,10,1)) -> 24485.93 | L12: =SUMIFS('Revenue Data'!$I$6:$I$445,'Revenue Data'!$H$6:$H$445,$A12,'Revenue Data'!$B$6:$B$445,DATE(2025,11,1)) -> 24607.81 | M12: =SUMIFS('Revenue Data'!$I$6:$I$445,'Revenue Data'!$H$6:$H$445,$A12,'Revenue Data'!$B$6:$B$445,DATE(2025,12,1)) -> 22274.63 | N12: =SUMIFS('Revenue Data'!$I$6:$I$445,'Revenue Data'!$H$6:$H$445,$A12,'Revenue Data'!$B$6:$B$445,DATE(2026,1,1)) -> 27372.84 | O12: =SUMIFS('Revenue Data'!$I$6:$I$445,'Revenue Data'!$H$6:$H$445,$A12,'Revenue Data'!$B$6:$B$445,DATE(2026,2,1)) -> 26976.11 | P12: =SUMIFS('Revenue Data'!$I$6:$I$445,'Revenue Data'!$H$6:$H$445,$A12,'Revenue Data'!$B$6:$B$445,DATE(2026,3,1)) -> 29109.71 | Q12: =SUMIFS('Revenue Data'!$I$6:$I$445,'Revenue Data'!$H$6:$H$445,$A12,'Revenue Data'!$B$6:$B$445,DATE(2026,4,1)) -> 29137.89 | R12: =SUMIFS('Revenue Data'!$I$6:$I$445,'Revenue Data'!$H$6:$H$445,$A12,'Revenue Data'!$B$6:$B$445,DATE(2026,5,1)) -> 30191.24 | S12: =SUMIFS('Revenue Data'!$I$6:$I$445,'Revenue Data'!$H$6:$H$445,$A12,'Revenue Data'!$B$6:$B$445,DATE(2026,6,1)) -> 29711.14 | T12: =SUMIFS('Revenue Data'!$I$6:$I$445,'Revenue Data'!$H$6:$H$445,$A12,'Revenue Data'!$B$6:$B$445,DATE(2026,7,1)) -> 28633.95 | U12: =SUMIFS('Revenue Data'!$I$6:$I$445,'Revenue Data'!$H$6:$H$445,$A12,'Revenue Data'!$B$6:$B$445,DATE(2026,8,1)) -> 26852.21 | V12: =SUMIFS('Revenue Data'!$I$6:$I$445,'Revenue Data'!$H$6:$H$445,$A12,'Revenue Data'!$B$6:$B$445,DATE(2026,9,1)) -> 29976.21

Sheet MoM & YoY
A1: Month-on-month and year-on-year revenue
A2: Total recognised revenue; plan = FY2026 operating plan (Jan 2026)
A3: Classification: Confidential
A5: Month | B5: Revenue (USD) | C5: MoM change | D5: MoM % | E5: Same month prior year | F5: YoY % | G5: FY2026 plan | H5: Variance to plan | I5: Gross margin %
A6: Jan-25 | B6: =SUMIFS('Revenue Data'!$I$6:$I$445,'Revenue Data'!$B$6:$B$445,DATE(2025,1,1)) -> 981516.84 | I6: =SUMPRODUCT(('Revenue Data'!$B$6:$B$445=DATE(2025,1,1))*'Revenue Data'!$I$6:$I$445*'Revenue Data'!$K$6:$K$445)/B6 -> 0.26554354
A7: Feb-25 | B7: =SUMIFS('Revenue Data'!$I$6:$I$445,'Revenue Data'!$B$6:$B$445,DATE(2025,2,1)) -> 1009677.5 | C7: =B7-B6 -> 28160.69 | D7: =IF(B6=0,"",B7/B6-1) -> 0.02869099 | I7: =SUMPRODUCT(('Revenue Data'!$B$6:$B$445=DATE(2025,2,1))*'Revenue Data'!$I$6:$I$445*'Revenue Data'!$K$6:$K$445)/B7 -> 0.26663486
A8: Mar-25 | B8: =SUMIFS('Revenue Data'!$I$6:$I$445,'Revenue Data'!$B$6:$B$445,DATE(2025,3,1)) -> 1273399.3 | C8: =B8-B7 -> 263721.75 | D8: =IF(B7=0,"",B8/B7-1) -> 0.26119404 | I8: =SUMPRODUCT(('Revenue Data'!$B$6:$B$445=DATE(2025,3,1))*'Revenue Data'!$I$6:$I$445*'Revenue Data'!$K$6:$K$445)/B8 -> 0.2605452
A9: Apr-25 | B9: =SUMIFS('Revenue Data'!$I$6:$I$445,'Revenue Data'!$B$6:$B$445,DATE(2025,4,1)) -> 1241155.9 | C9: =B9-B8 -> -32243.35 | D9: =IF(B8=0,"",B9/B8-1) -> -0.025320691 | I9: =SUMPRODUCT(('Revenue Data'!$B$6:$B$445=DATE(2025,4,1))*'Revenue Data'!$I$6:$I$445*'Revenue Data'!$K$6:$K$445)/B9 -> 0.25824615
A10: May-25 | B10: =SUMIFS('Revenue Data'!$I$6:$I$445,'Revenue Data'!$B$6:$B$445,DATE(2025,5,1)) -> 1260850.6 | C10: =B10-B9 -> 19694.62 | D10: =IF(B9=0,"",B10/B9-1) -> 0.015867966 | I10: =SUMPRODUCT(('Revenue Data'!$B$6:$B$445=DATE(2025,5,1))*'Revenue Data'!$I$6:$I$445*'Revenue Data'!$K$6:$K$445)/B10 -> 0.26254489
A11: Jun-25 | B11: =SUMIFS('Revenue Data'!$I$6:$I$445,'Revenue Data'!$B$6:$B$445,DATE(2025,6,1)) -> 1382635.9 | C11: =B11-B10 -> 121785.31 | D11: =IF(B10=0,"",B11/B10-1) -> 0.096589806 | I11: =SUMPRODUCT(('Revenue Data'!$B$6:$B$445=DATE(2025,6,1))*'Revenue Data'!$I$6:$I$445*'Revenue Data'!$K$6:$K$445)/B11 -> 0.26943325
A12: Jul-25 | B12: =SUMIFS('Revenue Data'!$I$6:$I$445,'Revenue Data'!$B$6:$B$445,DATE(2025,7,1)) -> 1308532.1 | C12: =B12-B11 -> -74103.75 | D12: =IF(B11=0,"",B12/B11-1) -> -0.053595999 | I12: =SUMPRODUCT(('Revenue Data'!$B$6:$B$445=DATE(2025,7,1))*'Revenue Data'!$I$6:$I$445*'Revenue Data'!$K$6:$K$445)/B12 -> 0.26856173
A13: Aug-25 | B13: =SUMIFS('Revenue Data'!$I$6:$I$445,'Revenue Data'!$B$6:$B$445,DATE(2025,8,1)) -> 1333061.6 | C13: =B13-B12 -> 24529.52 | D13: =IF(B12=0,"",B13/B12-1) -> 0.01874583 | I13: =SUMPRODUCT(('Revenue Data'!$B$6:$B$445=DATE(2025,8,1))*'Revenue Data'!$I$6:$I$445*'Revenue Data'!$K$6:$K$445)/B13 -> 0.27166624
A14: Sep-25 | B14: =SUMIFS('Revenue Data'!$I$6:$I$445,'Revenue Data'!$B$6:$B$445,DATE(2025,9,1)) -> 1471241.6 | C14: =B14-B13 -> 138179.98 | D14: =IF(B13=0,"",B14/B13-1) -> 0.10365611 | I14: =SUMPRODUCT(('Revenue Data'!$B$6:$B$445=DATE(2025,9,1))*'Revenue Data'!$I$6:$I$445*'Revenue Data'!$K$6:$K$445)/B14 -> 0.2696859
A15: Oct-25 | B15: =SUMIFS('Revenue Data'!$I$6:$I$445,'Revenue Data'!$B$6:$B$445,DATE(2025,10,1)) -> 1400065.1 | C15: =B15-B14 -> -71176.47 | D15: =IF(B14=0,"",B15/B14-1) -> -0.048378505 | I15: =SUMPRODUCT(('Revenue Data'!$B$6:$B$445=DATE(2025,10,1))*'Revenue Data'!$I$6:$I$445*'Revenue Data'!$K$6:$K$445)/B15 -> 0.27280264
A16: Nov-25 | B16: =SUMIFS('Revenue Data'!$I$6:$I$445,'Revenue Data'!$B$6:$B$445,DATE(2025,11,1)) -> 1404974.6 | C16: =B16-B15 -> 4909.46 | D16: =IF(B15=0,"",B16/B15-1) -> 0.003506594 | I16: =SUMPRODUCT(('Revenue Data'!$B$6:$B$445=DATE(2025,11,1))*'Revenue Data'!$I$6:$I$445*'Revenue Data'!$K$6:$K$445)/B16 -> 0.26697781
A17: Dec-25 | B17: =SUMIFS('Revenue Data'!$I$6:$I$445,'Revenue Data'!$B$6:$B$445,DATE(2025,12,1)) -> 1298369.9 | C17: =B17-B16 -> -106604.69 | D17: =IF(B16=0,"",B17/B16-1) -> -0.075876596 | I17: =SUMPRODUCT(('Revenue Data'!$B$6:$B$445=DATE(2025,12,1))*'Revenue Data'!$I$6:$I$445*'Revenue Data'!$K$6:$K$445)/B17 -> 0.26993269
A18: Jan-26 | B18: =SUMIFS('Revenue Data'!$I$6:$I$445,'Revenue Data'!$B$6:$B$445,DATE(2026,1,1)) -> 1489571.9 | C18: =B18-B17 -> 191201.98 | D18: =IF(B17=0,"",B18/B17-1) -> 0.1472631 | E18: =B6 -> 981516.84 | F18: =IF(E18=0,"",B18/E18-1) -> 0.51762235 | G18: 1516512 | H18: =B18-G18 -> -26940.11 | I18: =SUMPRODUCT(('Revenue Data'!$B$6:$B$445=DATE(2026,1,1))*'Revenue Data'!$I$6:$I$445*'Revenue Data'!$K$6:$K$445)/B18 -> 0.27182376
A19: Feb-26 | B19: =SUMIFS('Revenue Data'!$I$6:$I$445,'Revenue Data'!$B$6:$B$445,DATE(2026,2,1)) -> 1528885 | C19: =B19-B18 -> 39313.12 | D19: =IF(B18=0,"",B19/B18-1) -> 0.026392227 | E19: =B7 -> 1009677.5 | F19: =IF(E19=0,"",B19/E19-1) -> 0.51423099 | G19: 1581739 | H19: =B19-G19 -> -52853.99 | I19: =SUMPRODUCT(('Revenue Data'!$B$6:$B$445=DATE(2026,2,1))*'Revenue Data'!$I$6:$I$445*'Revenue Data'!$K$6:$K$445)/B19 -> 0.27286736
A20: Mar-26 | B20: =SUMIFS('Revenue Data'!$I$6:$I$445,'Revenue Data'!$B$6:$B$445,DATE(2026,3,1)) -> 1646620.2 | C20: =B20-B19 -> 117735.16 | D20: =IF(B19=0,"",B20/B19-1) -> 0.077007204 | E20: =B8 -> 1273399.3 | F20: =IF(E20=0,"",B20/E20-1) -> 0.29309023 | G20: 1695885 | H20: =B20-G20 -> -49264.83 | I20: =SUMPRODUCT(('Revenue Data'!$B$6:$B$445=DATE(2026,3,1))*'Revenue Data'!$I$6:$I$445*'Revenue Data'!$K$6:$K$445)/B20 -> 0.27143021
A21: Apr-26 | B21: =SUMIFS('Revenue Data'!$I$6:$I$445,'Revenue Data'!$B$6:$B$445,DATE(2026,4,1)) -> 1531668.9 | C21: =B21-B20 -> -114951.27 | D21: =IF(B20=0,"",B21/B20-1) -> -0.069810435 | E21: =B9 -> 1241155.9 | F21: =IF(E21=0,"",B21/E21-1) -> 0.23406646 | G21: 1614352 | H21: =B21-G21 -> -82683.1 | I21: =SUMPRODUCT(('Revenue Data'!$B$6:$B$445=DATE(2026,4,1))*'Revenue Data'!$I$6:$I$445*'Revenue Data'!$K$6:$K$445)/B21 -> 0.26918879
A22: May-26 | B22: =SUMIFS('Revenue Data'!$I$6:$I$445,'Revenue Data'!$B$6:$B$445,DATE(2026,5,1)) -> 1649910.5 | C22: =B22-B21 -> 118241.64 | D22: =IF(B21=0,"",B22/B21-1) -> 0.077197911 | E22: =B10 -> 1260850.6 | F22: =IF(E22=0,"",B22/E22-1) -> 0.30856947 | G22: 1659358 | H22: =B22-G22 -> -9447.46 | I22: =SUMPRODUCT(('Revenue Data'!$B$6:$B$445=DATE(2026,5,1))*'Revenue Data'!$I$6:$I$445*'Revenue Data'!$K$6:$K$445)/B22 -> 0.27330433
A23: Jun-26 | B23: =SUMIFS('Revenue Data'!$I$6:$I$445,'Revenue Data'!$B$6:$B$445,DATE(2026,6,1)) -> 1695551.9 | C23: =B23-B22 -> 45641.35 | D23: =IF(B22=0,"",B23/B22-1) -> 0.027662924 | E23: =B11 -> 1382635.9 | F23: =IF(E23=0,"",B23/E23-1) -> 0.22631847 | G23: 1725733 | H23: =B23-G23 -> -30181.11 | I23: =SUMPRODUCT(('Revenue Data'!$B$6:$B$445=DATE(2026,6,1))*'Revenue Data'!$I$6:$I$445*'Revenue Data'!$K$6:$K$445)/B23 -> 0.27602979
A24: Jul-26 | B24: =SUMIFS('Revenue Data'!$I$6:$I$445,'Revenue Data'!$B$6:$B$445,DATE(2026,7,1)) -> 1607194 | C24: =B24-B23 -> -88357.91 | D24: =IF(B23=0,"",B24/B23-1) -> -0.052111593 | E24: =B12 -> 1308532.1 | F24: =IF(E24=0,"",B24/E24-1) -> 0.22824191 | G24: 1600201 | H24: =B24-G24 -> 6992.98 | I24: =SUMPRODUCT(('Revenue Data'!$B$6:$B$445=DATE(2026,7,1))*'Revenue Data'!$I$6:$I$445*'Revenue Data'!$K$6:$K$445)/B24 -> 0.25134638
A25: Aug-26 | B25: =SUMIFS('Revenue Data'!$I$6:$I$445,'Revenue Data'!$B$6:$B$445,DATE(2026,8,1)) -> 1678319.6 | C25: =B25-B24 -> 71125.62 | D25: =IF(B24=0,"",B25/B24-1) -> 0.044254534 | E25: =B13 -> 1333061.6 | F25: =IF(E25=0,"",B25/E25-1) -> 0.25899626 | G25: 1670914 | H25: =B25-G25 -> 7405.6 | I25: =SUMPRODUCT(('Revenue Data'!$B$6:$B$445=DATE(2026,8,1))*'Revenue Data'!$I$6:$I$445*'Revenue Data'!$K$6:$K$445)/B25 -> 0.25307995
A26: Sep-26 | B26: =SUMIFS('Revenue Data'!$I$6:$I$445,'Revenue Data'!$B$6:$B$445,DATE(2026,9,1)) -> 1803914.6 | C26: =B26-B25 -> 125595.03 | D26: =IF(B25=0,"",B26/B25-1) -> 0.074833798 | E26: =B14 -> 1471241.6 | F26: =IF(E26=0,"",B26/E26-1) -> 0.22611719 | G26: 1739235 | H26: =B26-G26 -> 64679.63 | I26: =SUMPRODUCT(('Revenue Data'!$B$6:$B$445=DATE(2026,9,1))*'Revenue Data'!$I$6:$I$445*'Revenue Data'!$K$6:$K$445)/B26 -> 0.24586471

Sheet Account Summary
A1: Account summary - YTD vs prior YTD (Jan-Sep)
A2: Margin restricted to Sales Ops / Finance
A3: Classification: Confidential
A5: Account ID | B5: Account | C5: Industry | D5: Owner | E5: FY2025 revenue | F5: Jan-Sep 2025 | G5: Jan-Sep 2026 | H5: YoY growth | I5: GM % 2026 YTD | J5: Primary service line
A6: ACC-1001 | B6: Northwind Traders | C6: Retail | D6: Priya Raman | E6: =SUMIFS('Revenue Data'!$I$6:$I$445,'Revenue Data'!$D$6:$D$445,A6,'Revenue Data'!$C$6:$C$445,2025) -> 3745381.5 | F6: =SUMIFS('Revenue Data'!$I$6:$I$445,'Revenue Data'!$D$6:$D$445,A6,'Revenue Data'!$B$6:$B$445,">="&DATE(2025,1,1),'Revenue Data'!$B$6:$B$445,"<="&DATE(2025,9,1)) -> 2748701.2 | G6: =SUMIFS('Revenue Data'!$I$6:$I$445,'Revenue Data'!$D$6:$D$445,A6,'Revenue Data'!$C$6:$C$445,2026) -> 3020234.2 | H6: =IF(F6=0,"New",G6/F6-1) -> 0.098785951 | I6: 0.2039 | J6: Application Modernization
A7: ACC-1002 | B7: Fabrikam Health | C7: Healthcare | D7: Priya Raman | E7: =SUMIFS('Revenue Data'!$I$6:$I$445,'Revenue Data'!$D$6:$D$445,A7,'Revenue Data'!$C$6:$C$445,2025) -> 888831.58 | F7: =SUMIFS('Revenue Data'!$I$6:$I$445,'Revenue Data'!$D$6:$D$445,A7,'Revenue Data'!$B$6:$B$445,">="&DATE(2025,1,1),'Revenue Data'!$B$6:$B$445,"<="&DATE(2025,9,1)) -> 527247.13 | G7: =SUMIFS('Revenue Data'!$I$6:$I$445,'Revenue Data'!$D$6:$D$445,A7,'Revenue Data'!$C$6:$C$445,2026) -> 1613151.6 | H7: =IF(F7=0,"New",G7/F7-1) -> 2.0595739 | I7: 0.3067 | J7: Data & AI
A8: ACC-1003 | B8: Woodgrove Bank | C8: BFSI | D8: Marcus Bell | E8: =SUMIFS('Revenue Data'!$I$6:$I$445,'Revenue Data'!$D$6:$D$445,A8,'Revenue Data'!$C$6:$C$445,2025) -> 943149.88 | F8: =SUMIFS('Revenue Data'!$I$6:$I$445,'Revenue Data'!$D$6:$D$445,A8,'Revenue Data'!$B$6:$B$445,">="&DATE(2025,1,1),'Revenue Data'!$B$6:$B$445,"<="&DATE(2025,9,1)) -> 710284.77 | G8: =SUMIFS('Revenue Data'!$I$6:$I$445,'Revenue Data'!$D$6:$D$445,A8,'Revenue Data'!$C$6:$C$445,2026) -> 883783.59 | H8: =IF(F8=0,"New",G8/F8-1) -> 0.24426656 | I8: 0.287 | J8: Managed Services
A9: ACC-1004 | B9: Tailspin Airlines | C9: Travel & Transport | D9: Sophie Turner | E9: =SUMIFS('Revenue Data'!$I$6:$I$445,'Revenue Data'!$D$6:$D$445,A9,'Revenue Data'!$C$6:$C$445,2025) -> 1699403.3 | F9: =SUMIFS('Revenue Data'!$I$6:$I$445,'Revenue Data'!$D$6:$D$445,A9,'Revenue Data'!$B$6:$B$445,">="&DATE(2025,1,1),'Revenue Data'!$B$6:$B$445,"<="&DATE(2025,9,1)) -> 1288612.5 | G9: =SUMIFS('Revenue Data'!$I$6:$I$445,'Revenue Data'!$D$6:$D$445,A9,'Revenue Data'!$C$6:$C$445,2026) -> 1480735.8 | H9: =IF(F9=0,"New",G9/F9-1) -> 0.14909314 | I9: 0.2486 | J9: Cloud & Infrastructure
A10: ACC-1005 | B10: Litware Insurance | C10: BFSI | D10: Marcus Bell | E10: =SUMIFS('Revenue Data'!$I$6:$I$445,'Revenue Data'!$D$6:$D$445,A10,'Revenue Data'!$C$6:$C$445,2025) -> 293137.93 | F10: =SUMIFS('Revenue Data'!$I$6:$I$445,'Revenue Data'!$D$6:$D$445,A10,'Revenue Data'!$B$6:$B$445,">="&DATE(2025,1,1),'Revenue Data'!$B$6:$B$445,"<="&DATE(2025,9,1)) -> 221769.56 | G10: =SUMIFS('Revenue Data'!$I$6:$I$445,'Revenue Data'!$D$6:$D$445,A10,'Revenue Data'!$C$6:$C$445,2026) -> 257961.3 | H10: =IF(F10=0,"New",G10/F10-1) -> 0.16319526 | I10: 0.3066 | J10: Intelligent Automation
A11: ACC-1006 | B11: Contoso Manufacturing | C11: Manufacturing | D11: Sophie Turner | E11: =SUMIFS('Revenue Data'!$I$6:$I$445,'Revenue Data'!$D$6:$D$445,A11,'Revenue Data'!$C$6:$C$445,2025) -> 1393310.2 | F11: =SUMIFS('Revenue Data'!$I$6:$I$445,'Revenue Data'!$D$6:$D$445,A11,'Revenue Data'!$B$6:$B$445,">="&DATE(2025,1,1),'Revenue Data'!$B$6:$B$445,"<="&DATE(2025,9,1)) -> 1056976.3 | G11: =SUMIFS('Revenue Data'!$I$6:$I$445,'Revenue Data'!$D$6:$D$445,A11,'Revenue Data'!$C$6:$C$445,2026) -> 983613.58 | H11: =IF(F11=0,"New",G11/F11-1) -> -0.06940813 | I11: 0.2424 | J11: Application Modernization
A12: ACC-1007 | B12: Adventure Works Retail | C12: Retail | D12: James Patel | E12: =SUMIFS('Revenue Data'!$I$6:$I$445,'Revenue Data'!$D$6:$D$445,A12,'Revenue Data'!$C$6:$C$445,2025) -> 591446.65 | F12: =SUMIFS('Revenue Data'!$I$6:$I$445,'Revenue Data'!$D$6:$D$445,A12,'Revenue Data'!$B$6:$B$445,">="&DATE(2025,1,1),'Revenue Data'!$B$6:$B$445,"<="&DATE(2025,9,1)) -> 444151.05 | G12: =SUMIFS('Revenue Data'!$I$6:$I$445,'Revenue Data'!$D$6:$D$445,A12,'Revenue Data'!$C$6:$C$445,2026) -> 526925.86 | H12: =IF(F12=0,"New",G12/F12-1) -> 0.18636635 | I12: 0.2449 | J12: Digital Commerce
A13: ACC-1008 | B13: Wingtip Logistics | C13: Logistics | D13: Sophie Turner | E13: =SUMIFS('Revenue Data'!$I$6:$I$445,'Revenue Data'!$D$6:$D$445,A13,'Revenue Data'!$C$6:$C$445,2025) -> 707419.22 | F13: =SUMIFS('Revenue Data'!$I$6:$I$445,'Revenue Data'!$D$6:$D$445,A13,'Revenue Data'!$B$6:$B$445,">="&DATE(2025,1,1),'Revenue Data'!$B$6:$B$445,"<="&DATE(2025,9,1)) -> 444857.89 | G13: =SUMIFS('Revenue Data'!$I$6:$I$445,'Revenue Data'!$D$6:$D$445,A13,'Revenue Data'!$C$6:$C$445,2026) -> 1329908.7 | H13: =IF(F13=0,"New",G13/F13-1) -> 1.9895136 | I13: 0.3198 | J13: Data & AI
A14: ACC-1009 | B14: Relecloud | C14: Telecom | D14: James Patel | E14: =SUMIFS('Revenue Data'!$I$6:$I$445,'Revenue Data'!$D$6:$D$445,A14,'Revenue Data'!$C$6:$C$445,2025) -> 2170451.3 | F14: =SUMIFS('Revenue Data'!$I$6:$I$445,'Revenue Data'!$D$6:$D$445,A14,'Revenue Data'!$B$6:$B$445,">="&DATE(2025,1,1),'Revenue Data'!$B$6:$B$445,"<="&DATE(2025,9,1)) -> 1643587.4 | G14: =SUMIFS('Revenue Data'!$I$6:$I$445,'Revenue Data'!$D$6:$D$445,A14,'Revenue Data'!$C$6:$C$445,2026) -> 1714616.9 | H14: =IF(F14=0,"New",G14/F14-1) -> 0.043216113 | I14: 0.2794 | J14: Managed Services
A15: ACC-1010 | B15: Lamna Healthcare | C15: Healthcare | D15: Hannah Lee | E15: =SUMIFS('Revenue Data'!$I$6:$I$445,'Revenue Data'!$D$6:$D$445,A15,'Revenue Data'!$C$6:$C$445,2025) -> 1084246.1 | F15: =SUMIFS('Revenue Data'!$I$6:$I$445,'Revenue Data'!$D$6:$D$445,A15,'Revenue Data'!$B$6:$B$445,">="&DATE(2025,1,1),'Revenue Data'!$B$6:$B$445,"<="&DATE(2025,9,1)) -> 815870.39 | G15: =SUMIFS('Revenue Data'!$I$6:$I$445,'Revenue Data'!$D$6:$D$445,A15,'Revenue Data'!$C$6:$C$445,2026) -> 849738.07 | H15: =IF(F15=0,"New",G15/F15-1) -> 0.041511103 | I15: 0.2721 | J15: Cloud & Infrastructure
A16: ACC-1011 | B16: Wide World Importers | C16: Retail | D16: James Patel | E16: =SUMIFS('Revenue Data'!$I$6:$I$445,'Revenue Data'!$D$6:$D$445,A16,'Revenue Data'!$C$6:$C$445,2025) -> 1048403.7 | F16: =SUMIFS('Revenue Data'!$I$6:$I$445,'Revenue Data'!$D$6:$D$445,A16,'Revenue Data'!$B$6:$B$445,">="&DATE(2025,1,1),'Revenue Data'!$B$6:$B$445,"<="&DATE(2025,9,1)) -> 793603.13 | G16: =SUMIFS('Revenue Data'!$I$6:$I$445,'Revenue Data'!$D$6:$D$445,A16,'Revenue Data'!$C$6:$C$445,2026) -> 760775.64 | H16: =IF(F16=0,"New",G16/F16-1) -> -0.041365122 | I16: 0.2516 | J16: Managed Services
A17: ACC-1012 | B17: Trey Research | C17: Life Sciences | D17: Hannah Lee | E17: =SUMIFS('Revenue Data'!$I$6:$I$445,'Revenue Data'!$D$6:$D$445,A17,'Revenue Data'!$C$6:$C$445,2025) -> 349651.6 | F17: =SUMIFS('Revenue Data'!$I$6:$I$445,'Revenue Data'!$D$6:$D$445,A17,'Revenue Data'!$B$6:$B$445,">="&DATE(2025,1,1),'Revenue Data'!$B$6:$B$445,"<="&DATE(2025,9,1)) -> 263209.7 | G17: =SUMIFS('Revenue Data'!$I$6:$I$445,'Revenue Data'!$D$6:$D$445,A17,'Revenue Data'!$C$6:$C$445,2026) -> 383531.16 | H17: =IF(F17=0,"New",G17/F17-1) -> 0.45713156 | I17: 0.3352 | J17: Data & AI
... A21: ACC-1018 | B21: Proseware Inc | C21: Technology | D21: Hannah Lee | E21: =SUMIFS('Revenue Data'!$I$6:$I$445,'Revenue Data'!$D$6:$D$445,A21,'Revenue Data'!$C$6:$C$445,2025) -> 0 | F21: =SUMIFS('Revenue Data'!$I$6:$I$445,'Revenue Data'!$D$6:$D$445,A21,'Revenue Data'!$B$6:$B$445,">="&DATE(2025,1,1),'Revenue Data'!$B$6:$B$445,"<="&DATE(2025,9,1)) -> 0 | G21: =SUMIFS('Revenue Data'!$I$6:$I$445,'Revenue Data'!$D$6:$D$445,A21,'Revenue Data'!$C$6:$C$445,2026) -> 49024.02 | H21: =IF(F21=0,"New",G21/F21-1) -> New | I21: 0.2205 | J21: Application Modernization
A24: Month filters use the Month start date column of Revenue Data.
A25: GM % below 15% is highlighted. Northwind's Atlas fixed-price overrun took Application Modernization margin negative in September 2026.
